{
  "law_id": "010382",
  "mst": "286445",
  "version_uid": "010382:286445:20260602",
  "law_name": "사행산업통합감독위원회법",
  "law_abbr": "",
  "law_type": "법률",
  "promulgation_no": "21748",
  "promulgation_date": "20260602",
  "enforcement_date": "20260602",
  "revision_date": "20260602",
  "revision_type": "일부개정",
  "is_current": true,
  "is_future": false,
  "basic_info": {
    "법령명_한글": "사행산업통합감독위원회법",
    "공포번호": "21748",
    "전화번호": "02-3704-0511",
    "언어": "한글",
    "제개정구분": "일부개정",
    "법령ID": "010382",
    "공동부령정보": "",
    "소관부처": {
      "content": "문화체육관광부",
      "소관부처코드": "1371000"
    },
    "공포법령여부": "N",
    "법종구분": {
      "content": "법률",
      "법종구분코드": "A0002"
    },
    "시행일자": "20260602",
    "연락부서": {
      "부서단위": {
        "부서연락처": "02-3704-0511",
        "부서키": "419485",
        "부서명": "사행산업통합감독위원회 기획총괄과",
        "소관부처명": "문화체육관광부",
        "소관부처코드": "1371000"
      }
    },
    "법령명_한자": "사행산업통합감독위원회법",
    "법령명약칭": "",
    "공포일자": "20260602",
    "편장절관": "17010000"
  },
  "amendment_text": "국회에서 의결된 사행산업통합감독위원회법 일부개정법률을 이에 공포한다.\n대통령        이재명 (인)\n2026년 6월 2일\n국무총리        김민석\n국무위원 문화체육관광부 장관        최휘영\n⊙법률 제21748호\n사행산업통합감독위원회법 일부개정법률\n사행산업통합감독위원회법 일부를 다음과 같이 개정한다.\n제14조의2제10항을 제12항으로 하고, 같은 조에 제10항 및 제11항을 각각 다음과 같이 신설한다.\n⑩ 부담금을 부과받은 사행산업사업자가 부과받은 사항에 대하여 이의가 있는 경우에는 제3항에 따른 통지를 받은 날부터 30일 이내에 위원회에 이의신청을 할 수 있다. 이 경우 위원회는 이의신청을 받은 날부터 60일 이내에 위원회의 의결을 거쳐 그 결과를 신청인에게 통지하여야 한다.\n⑪ 제10항에서 규정한 사항 외에 이의신청에 관한 사항은 「행정기본법」 제36조(같은 조 제2항 단서는 제외한다)에 따른다.\n부칙\n제1조(시행일) 이 법은 공포한 날부터 시행한다.\n제2조(이의신청에 관한 적용례) 제14조의2의 개정규정은 이 법 시행 이후 부과ㆍ징수하는 부담금부터 적용한다.",
  "revision_reason": "[일부개정]\n◇ 개정이유 및 주요내용\n대통령령에서 규정하고 있는 중독예방치유부담금 부과에 대한 이의신청제도를 법률로 상향하여 규정하고, 이 법에서 규정하고 있지 아니한 이의신청에 관한 사항에 대해서는 「행정기본법」에 따르도록 하여 중독예방치유부담금의 부과에 대한 이의신청제도의 법 적용 관계를 명확히 하려는 것임.\n<법제처 제공>",
  "body": {
    "format": "articles",
    "article_count": 31,
    "articles": [
      {
        "article_no": "제1조",
        "article_title": "목적",
        "chapter": "",
        "content": "제1조(목적) 이 법은 사행산업통합감독위원회를 설치하여 사행산업으로 인한 부작용 최소화와 불법사행산업에 대한 감시를 통하여 사행산업이 건전한 여가 및 레저산업으로 발전해 나가도록 함으로써 국민의 복지증진에 이바지함을 목적으로 한다. <개정 2012.5.23>",
        "enforcement_date": "20260602",
        "relations": [],
        "images": [],
        "provision_id": "law:사행산업통합감독위원회법#JO0001"
      },
      {
        "article_no": "제2조",
        "article_title": "정의",
        "chapter": "",
        "content": "제2조(정의) 이 법에서 사용하는 용어의 정의는 다음과 같다. <개정 2012.5.23, 2025.12.30>\n1.  \"사행산업\"이라 함은 다음 각 목의 규정에 따른 것을 말한다.\n가.  카지노업 : 「관광진흥법」과 「석탄산업전환지역 개발 지원에 관한 특별법」의 규정에 따른 카지노업\n나.  경마 : 「한국마사회법」의 규정에 따른 경마\n다.  경륜ㆍ경정 : 「경륜ㆍ경정법」의 규정에 따른 경륜과 경정\n라.  복권 : 「복권 및 복권기금법」의 규정에 따른 복권\n마.  체육진흥투표권 : 「국민체육진흥법」의 규정에 따른 체육진흥투표권\n바.  소싸움경기: 「전통 소싸움경기에 관한 법률」에 따른 소싸움경기\n2.  \"사행산업사업자\"라 함은 다음 각 목의 규정에 따른 자를 말한다.\n가.  「관광진흥법」과 「석탄산업전환지역 개발 지원에 관한 특별법」의 규정에 따른 카지노사업자\n나.  「한국마사회법」의 규정에 따른 한국마사회\n다.  「경륜ㆍ경정법」의 규정에 따른 경주사업자\n라.  「복권 및 복권기금법」의 규정에 따른 복권사업자\n마.  「국민체육진흥법」의 규정에 따른 서울올림픽기념국민체육진흥공단과 수탁사업자\n바.  「전통 소싸움경기에 관한 법률」에 따른 소싸움경기시행자와 수탁사업자\n3.  \"불법사행산업\"이란 다음 각 목의 어느 하나에 해당하는 행위를 업으로 하는 행위를 말한다.\n가.  제1호 각 목의 법률에서 해당 사행산업과 관련하여 금지 또는 제한하는 행위\n나.  「게임산업진흥에 관한 법률」에 따른 사행성게임물을 이용하여 사람들이 사행행위를 할 수 있게 서비스를 제공하는 행위\n다.  「정보통신망 이용촉진 및 정보보호 등에 관한 법률」에 따른 정보통신망을 통하여 사람들이 사행행위를 할 수 있게 서비스를 제공하는 행위(제1호에 따른 사행산업 및 「사행행위 등 규제 및 처벌 특례법」에 따른 사행행위영업은 제외한다)",
        "enforcement_date": "20260602",
        "relations": [
          {
            "relation_type": "citation",
            "delegation_type": null,
            "target_category": "법령",
            "source_article_no": "제2조",
            "source_clause": "제2조",
            "link_text": "「관광진흥법」",
            "line_text": "",
            "target_law_name": "관광진흥법",
            "target_article_no": "",
            "target_article_title": "",
            "target_mst": "279659",
            "target_url": "https://www.law.go.kr/법령/관광진흥법",
            "resolve_method": "rendered_link",
            "source_provision_id": "law:사행산업통합감독위원회법#JO0002",
            "reference_id": "law:관광진흥법#DOC"
          },
          {
            "relation_type": "citation",
            "delegation_type": null,
            "target_category": "법령",
            "source_article_no": "제2조",
            "source_clause": "제2조",
            "link_text": "「석탄산업전환지역 개발 지원에 관한 특별법」",
            "line_text": "",
            "target_law_name": "석탄산업전환지역개발지원에관한특별법",
            "target_article_no": "",
            "target_article_title": "",
            "target_mst": "281897",
            "target_url": "https://www.law.go.kr/법령/석탄산업전환지역개발지원에관한특별법",
            "resolve_method": "rendered_link",
            "source_provision_id": "law:사행산업통합감독위원회법#JO0002",
            "reference_id": "law:석탄산업전환지역개발지원에관한특별법#DOC"
          },
          {
            "relation_type": "citation",
            "delegation_type": null,
            "target_category": "법령",
            "source_article_no": "제2조",
            "source_clause": "제2조",
            "link_text": "「한국마사회법」",
            "line_text": "",
            "target_law_name": "한국마사회법",
            "target_article_no": "",
            "target_article_title": "",
            "target_mst": "265371",
            "target_url": "https://www.law.go.kr/법령/한국마사회법",
            "resolve_method": "rendered_link",
            "source_provision_id": "law:사행산업통합감독위원회법#JO0002",
            "reference_id": "law:한국마사회법#DOC"
          },
          {
            "relation_type": "citation",
            "delegation_type": null,
            "target_category": "법령",
            "source_article_no": "제2조",
            "source_clause": "제2조",
            "link_text": "「경륜ㆍ경정법」",
            "line_text": "",
            "target_law_name": "경륜ㆍ경정법",
            "target_article_no": "",
            "target_article_title": "",
            "target_mst": "253533",
            "target_url": "https://www.law.go.kr/법령/경륜ㆍ경정법",
            "resolve_method": "rendered_link",
            "source_provision_id": "law:사행산업통합감독위원회법#JO0002",
            "reference_id": "law:경륜경정법#DOC"
          },
          {
            "relation_type": "citation",
            "delegation_type": null,
            "target_category": "법령",
            "source_article_no": "제2조",
            "source_clause": "제2조",
            "link_text": "「복권 및 복권기금법」",
            "line_text": "",
            "target_law_name": "복권및복권기금법",
            "target_article_no": "",
            "target_article_title": "",
            "target_mst": "276115",
            "target_url": "https://www.law.go.kr/법령/복권및복권기금법",
            "resolve_method": "rendered_link",
            "source_provision_id": "law:사행산업통합감독위원회법#JO0002",
            "reference_id": "law:복권및복권기금법#DOC"
          },
          {
            "relation_type": "citation",
            "delegation_type": null,
            "target_category": "법령",
            "source_article_no": "제2조",
            "source_clause": "제2조",
            "link_text": "「국민체육진흥법」",
            "line_text": "",
            "target_law_name": "국민체육진흥법",
            "target_article_no": "",
            "target_article_title": "",
            "target_mst": "286627",
            "target_url": "https://www.law.go.kr/법령/국민체육진흥법",
            "resolve_method": "rendered_link",
            "source_provision_id": "law:사행산업통합감독위원회법#JO0002",
            "reference_id": "law:국민체육진흥법#DOC"
          },
          {
            "relation_type": "citation",
            "delegation_type": null,
            "target_category": "법령",
            "source_article_no": "제2조",
            "source_clause": "제2조",
            "link_text": "「전통 소싸움경기에 관한 법률」",
            "line_text": "",
            "target_law_name": "전통소싸움경기에관한법률",
            "target_article_no": "",
            "target_article_title": "",
            "target_mst": "241979",
            "target_url": "https://www.law.go.kr/법령/전통소싸움경기에관한법률",
            "resolve_method": "rendered_link",
            "source_provision_id": "law:사행산업통합감독위원회법#JO0002",
            "reference_id": "law:전통소싸움경기에관한법률#DOC"
          },
          {
            "relation_type": "citation",
            "delegation_type": null,
            "target_category": "법령",
            "source_article_no": "제2조",
            "source_clause": "제2조",
            "link_text": "「관광진흥법」",
            "line_text": "",
            "target_law_name": "관광진흥법",
            "target_article_no": "",
            "target_article_title": "",
            "target_mst": "279659",
            "target_url": "https://www.law.go.kr/법령/관광진흥법",
            "resolve_method": "rendered_link",
            "source_provision_id": "law:사행산업통합감독위원회법#JO0002",
            "reference_id": "law:관광진흥법#DOC"
          },
          {
            "relation_type": "citation",
            "delegation_type": null,
            "target_category": "법령",
            "source_article_no": "제2조",
            "source_clause": "제2조",
            "link_text": "「석탄산업전환지역 개발 지원에 관한 특별법」",
            "line_text": "",
            "target_law_name": "석탄산업전환지역개발지원에관한특별법",
            "target_article_no": "",
            "target_article_title": "",
            "target_mst": "281897",
            "target_url": "https://www.law.go.kr/법령/석탄산업전환지역개발지원에관한특별법",
            "resolve_method": "rendered_link",
            "source_provision_id": "law:사행산업통합감독위원회법#JO0002",
            "reference_id": "law:석탄산업전환지역개발지원에관한특별법#DOC"
          },
          {
            "relation_type": "citation",
            "delegation_type": null,
            "target_category": "법령",
            "source_article_no": "제2조",
            "source_clause": "제2조",
            "link_text": "「한국마사회법」",
            "line_text": "",
            "target_law_name": "한국마사회법",
            "target_article_no": "",
            "target_article_title": "",
            "target_mst": "265371",
            "target_url": "https://www.law.go.kr/법령/한국마사회법",
            "resolve_method": "rendered_link",
            "source_provision_id": "law:사행산업통합감독위원회법#JO0002",
            "reference_id": "law:한국마사회법#DOC"
          },
          {
            "relation_type": "citation",
            "delegation_type": null,
            "target_category": "법령",
            "source_article_no": "제2조",
            "source_clause": "제2조",
            "link_text": "「경륜ㆍ경정법」",
            "line_text": "",
            "target_law_name": "경륜ㆍ경정법",
            "target_article_no": "",
            "target_article_title": "",
            "target_mst": "253533",
            "target_url": "https://www.law.go.kr/법령/경륜ㆍ경정법",
            "resolve_method": "rendered_link",
            "source_provision_id": "law:사행산업통합감독위원회법#JO0002",
            "reference_id": "law:경륜경정법#DOC"
          },
          {
            "relation_type": "citation",
            "delegation_type": null,
            "target_category": "법령",
            "source_article_no": "제2조",
            "source_clause": "제2조",
            "link_text": "「복권 및 복권기금법」",
            "line_text": "",
            "target_law_name": "복권및복권기금법",
            "target_article_no": "",
            "target_article_title": "",
            "target_mst": "276115",
            "target_url": "https://www.law.go.kr/법령/복권및복권기금법",
            "resolve_method": "rendered_link",
            "source_provision_id": "law:사행산업통합감독위원회법#JO0002",
            "reference_id": "law:복권및복권기금법#DOC"
          },
          {
            "relation_type": "citation",
            "delegation_type": null,
            "target_category": "법령",
            "source_article_no": "제2조",
            "source_clause": "제2조",
            "link_text": "「국민체육진흥법」",
            "line_text": "",
            "target_law_name": "국민체육진흥법",
            "target_article_no": "",
            "target_article_title": "",
            "target_mst": "286627",
            "target_url": "https://www.law.go.kr/법령/국민체육진흥법",
            "resolve_method": "rendered_link",
            "source_provision_id": "law:사행산업통합감독위원회법#JO0002",
            "reference_id": "law:국민체육진흥법#DOC"
          },
          {
            "relation_type": "citation",
            "delegation_type": null,
            "target_category": "법령",
            "source_article_no": "제2조",
            "source_clause": "제2조",
            "link_text": "「전통 소싸움경기에 관한 법률」",
            "line_text": "",
            "target_law_name": "전통소싸움경기에관한법률",
            "target_article_no": "",
            "target_article_title": "",
            "target_mst": "241979",
            "target_url": "https://www.law.go.kr/법령/전통소싸움경기에관한법률",
            "resolve_method": "rendered_link",
            "source_provision_id": "law:사행산업통합감독위원회법#JO0002",
            "reference_id": "law:전통소싸움경기에관한법률#DOC"
          },
          {
            "relation_type": "citation",
            "delegation_type": null,
            "target_category": "법령",
            "source_article_no": "제2조",
            "source_clause": "제2조",
            "link_text": "「게임산업진흥에 관한 법률」",
            "line_text": "",
            "target_law_name": "게임산업진흥에관한법률",
            "target_article_no": "",
            "target_article_title": "",
            "target_mst": "265811",
            "target_url": "https://www.law.go.kr/법령/게임산업진흥에관한법률",
            "resolve_method": "rendered_link",
            "source_provision_id": "law:사행산업통합감독위원회법#JO0002",
            "reference_id": "law:게임산업진흥에관한법률#DOC"
          },
          {
            "relation_type": "citation",
            "delegation_type": null,
            "target_category": "법령",
            "source_article_no": "제2조",
            "source_clause": "제2조",
            "link_text": "「정보통신망 이용촉진 및 정보보호 등에 관한 법률」",
            "line_text": "",
            "target_law_name": "정보통신망이용촉진및정보보호등에관한법률",
            "target_article_no": "",
            "target_article_title": "",
            "target_mst": "282481",
            "target_url": "https://www.law.go.kr/법령/정보통신망이용촉진및정보보호등에관한법률",
            "resolve_method": "rendered_link",
            "source_provision_id": "law:사행산업통합감독위원회법#JO0002",
            "reference_id": "law:정보통신망이용촉진및정보보호등에관한법률#DOC"
          },
          {
            "relation_type": "citation",
            "delegation_type": null,
            "target_category": "법령",
            "source_article_no": "제2조",
            "source_clause": "제2조",
            "link_text": "「사행행위 등 규제 및 처벌 특례법」",
            "line_text": "",
            "target_law_name": "사행행위등규제및처벌특례법",
            "target_article_no": "",
            "target_article_title": "",
            "target_mst": "257335",
            "target_url": "https://www.law.go.kr/법령/사행행위등규제및처벌특례법",
            "resolve_method": "rendered_link",
            "source_provision_id": "law:사행산업통합감독위원회법#JO0002",
            "reference_id": "law:사행행위등규제및처벌특례법#DOC"
          }
        ],
        "images": [],
        "provision_id": "law:사행산업통합감독위원회법#JO0002"
      },
      {
        "article_no": "제3조",
        "article_title": "다른 법률과의 관계",
        "chapter": "",
        "content": "제3조(다른 법률과의 관계) 사행산업의 과도한 사행심 유발을 억제하고 그 부작용의 예방과 치유 등에 관하여 다른 법률에 특별한 규정이 있는 경우를 제외하고는 이 법이 정하는 바에 따른다.",
        "enforcement_date": "20260602",
        "relations": [],
        "images": [],
        "provision_id": "law:사행산업통합감독위원회법#JO0003"
      },
      {
        "article_no": "제4조",
        "article_title": "사행산업통합감독위원회의 설치와 그 지위",
        "chapter": "",
        "content": "제4조(사행산업통합감독위원회의 설치와 그 지위)\n①사행산업에 관한 감독 업무와 불법사행산업에 관한 감시 업무를 효율적으로 수행하기 위하여 국무총리 소속하에 사행산업통합감독위원회(이하 \"위원회\"라 한다)를 둔다. <개정 2012.5.23>\n②위원회는 그 권한에 속하는 사무를 독립적으로 수행한다.",
        "enforcement_date": "20260602",
        "relations": [],
        "images": [],
        "provision_id": "law:사행산업통합감독위원회법#JO0004"
      },
      {
        "article_no": "제5조",
        "article_title": "위원회의 기능",
        "chapter": "",
        "content": "제5조(위원회의 기능)\n①위원회는 다음 각 호의 업무를 소관으로 한다. <개정 2012.5.23, 2017.12.19, 2019.11.26, 2025.11.11>\n1.  사행산업의 통합적인 관리ㆍ감독 및 건전화와 불법사행산업의 근절을 위한 종합계획의 수립ㆍ시행에 관한 사항\n2.  사행산업 업종 간의 통합 또는 개별 사행산업 업종의 영업장의 수, 매출액 규모 등에 관한 총량의 적용 또는 조정(계획수립을 포함한다. 이하 같다)이 필요한 경우로서 사행산업 관련 기관ㆍ단체 또는 개별 업계 등의 요청에 의한 협의ㆍ조정 또는 권고에 관한 사항\n3.  과도한 사행심 유발 방지를 위하여 사행산업사업자에 대한 현장 실태 확인과 지도ㆍ감독에 관한 사항\n4.  불법사행산업의 감시에 관한 사항\n5.  사행산업 및 불법사행산업으로 인한 중독 및 도박 문제의 예방과 치유 등 사회적 부작용 해소를 위한 대책의 수립ㆍ시행에 관한 사항\n6.  「국민체육진흥법」 제19조제2항에 따른 사행산업중독예방치유계정(이하 \"사행산업중독예방치유계정\"이라 한다)의 관리ㆍ운용에 관한 사항\n7.  사행산업을 건전한 레저산업으로 발전시키고 불법사행산업을 근절하는 데 필요한 조사ㆍ연구 및 평가에 관한 사항\n8.  사행산업에 대한 사회적 인식전환과 과도한 사행행위 유발 방지를 위한 통합적인 교육 프로그램 개발과 홍보에 관한 사항\n9.  청소년을 대상으로 한 도박 예방 교육(이하 \"청소년 도박예방교육\"이라 한다)의 실시에 관한 사항\n10.  위원회 운영 규칙 제정과 개정에 관한 사항\n11.  그 밖에 이 법 또는 다른 법률의 규정에 따라 위원회의 직무 또는 권한으로 규정된 사항\n②제1항제2호의 규정에 따른 사행산업 업종 간의 통합 또는 개별 사행산업 업종의 영업장의 수, 매출액 규모 등에 관한 총량의 적용 및 조정의 기준 등에 관한 구체적인 사항은 대통령령으로 정한다. <개정 2012.5.23>",
        "enforcement_date": "20260602",
        "relations": [
          {
            "relation_type": "citation",
            "delegation_type": null,
            "target_category": "법령",
            "source_article_no": "제5조",
            "source_clause": "제5조",
            "link_text": "「국민체육진흥법」",
            "line_text": "",
            "target_law_name": "국민체육진흥법",
            "target_article_no": "",
            "target_article_title": "",
            "target_mst": "286627",
            "target_url": "https://www.law.go.kr/법령/국민체육진흥법",
            "resolve_method": "rendered_link",
            "source_provision_id": "law:사행산업통합감독위원회법#JO0005",
            "reference_id": "law:국민체육진흥법#DOC"
          },
          {
            "relation_type": "citation",
            "delegation_type": null,
            "target_category": "법령",
            "source_article_no": "제5조",
            "source_clause": "제5조",
            "link_text": "제19조",
            "line_text": "",
            "target_law_name": "국민체육진흥법",
            "target_article_no": "제19조",
            "target_article_title": "기금의 설치 등",
            "target_mst": "286627",
            "target_url": "https://www.law.go.kr/법령/국민체육진흥법/제19조",
            "resolve_method": "rendered_link",
            "source_provision_id": "law:사행산업통합감독위원회법#JO0005",
            "reference_id": "law:국민체육진흥법#JO0019"
          },
          {
            "relation_type": "citation",
            "delegation_type": null,
            "target_category": "법령",
            "source_article_no": "제5조",
            "source_clause": "제5조",
            "link_text": "제2항",
            "line_text": "",
            "target_law_name": "국민체육진흥법",
            "target_article_no": "제19조",
            "target_article_title": "기금의 설치 등",
            "target_mst": "286627",
            "target_url": "https://www.law.go.kr/법령/국민체육진흥법/제19조",
            "resolve_method": "rendered_link",
            "source_provision_id": "law:사행산업통합감독위원회법#JO0005",
            "reference_id": "law:국민체육진흥법#JO0019"
          },
          {
            "relation_type": "delegation",
            "delegation_type": "시행령",
            "target_category": "법령",
            "source_article_no": "제5조",
            "source_clause": "제5조제2항",
            "link_text": "대통령령",
            "line_text": "대통령령으로",
            "target_law_name": "사행산업통합감독위원회법 시행령",
            "target_article_no": "제2조",
            "target_article_title": "총량기준 등",
            "target_mst": "284761",
            "target_url": "https://www.law.go.kr/법령/사행산업통합감독위원회법 시행령/제2조",
            "resolve_method": "lsDelegated",
            "source_provision_id": "law:사행산업통합감독위원회법#JO0005",
            "reference_id": "law:사행산업통합감독위원회법시행령#JO0002"
          }
        ],
        "images": [],
        "provision_id": "law:사행산업통합감독위원회법#JO0005"
      },
      {
        "article_no": "제6조",
        "article_title": "위원회의 구성",
        "chapter": "",
        "content": "제6조(위원회의 구성)\n①위원회는 위원장 1인을 포함하여 15인 이내의 위원으로 구성한다.\n② 위원회의 위원은 기획예산처차관, 행정안전부차관, 문화체육관광부의 사행산업에 관한 사무를 소관하는 차관과 농림축산식품부차관을 당연직으로 하고, 다음 각 호의 어느 하나에 해당하는 자 중에서 문화체육관광부장관ㆍ농림축산식품부장관 및 복권위원회 위원장의 추천을 받은 자를 포함하여 국무총리가 임명하거나 위촉한다. 이 경우 위원장은 당연직이 아닌 위원 중에서 국무총리가 지명하고 위원은 당연직이 아닌 자가 과반수 이상이 되도록 하여야 한다. <개정 2008.2.29, 2012.5.23, 2013.3.23, 2014.11.19, 2017.7.26, 2023.6.20, 2025.10.1>\n1.  판사ㆍ검사ㆍ변호사 또는 공인회계사의 자격이 있는 자\n2.  대학이나 공인된 연구기관에서 부교수 이상의 직이나 이에 상당하는 직에 있거나 있었던 자로서 사행산업 관련 분야(관광, 정보기술, 도박중독의 예방ㆍ치유 등 정신보건 분야를 포함한다. 이하 같다)를 전공한 자\n3.  사행산업 관련 분야의 학식과 경험이 풍부하고 덕망을 갖춘 자\n4.  사행산업 관련 분야의 전문성을 갖춘 자로서 비영리민간단체(「비영리민간단체 지원법」 제2조의 규정에 따른 민간단체를 말한다)에서 추천한 자\n③위원회의 위원은 비상임으로 한다.",
        "enforcement_date": "20260602",
        "relations": [
          {
            "relation_type": "citation",
            "delegation_type": null,
            "target_category": "법령",
            "source_article_no": "제6조",
            "source_clause": "제6조",
            "link_text": "「비영리민간단체 지원법」",
            "line_text": "",
            "target_law_name": "비영리민간단체지원법",
            "target_article_no": "",
            "target_article_title": "",
            "target_mst": "241935",
            "target_url": "https://www.law.go.kr/법령/비영리민간단체지원법",
            "resolve_method": "rendered_link",
            "source_provision_id": "law:사행산업통합감독위원회법#JO0006",
            "reference_id": "law:비영리민간단체지원법#DOC"
          },
          {
            "relation_type": "citation",
            "delegation_type": null,
            "target_category": "법령",
            "source_article_no": "제6조",
            "source_clause": "제6조",
            "link_text": "제2조",
            "line_text": "",
            "target_law_name": "비영리민간단체 지원법",
            "target_article_no": "제2조",
            "target_article_title": "정의",
            "target_mst": "241935",
            "target_url": "https://www.law.go.kr/법령/비영리민간단체 지원법/제2조",
            "resolve_method": "rendered_link",
            "source_provision_id": "law:사행산업통합감독위원회법#JO0006",
            "reference_id": "law:비영리민간단체지원법#JO0002"
          }
        ],
        "images": [],
        "provision_id": "law:사행산업통합감독위원회법#JO0006"
      },
      {
        "article_no": "제7조",
        "article_title": "위원장의 직무",
        "chapter": "",
        "content": "제7조(위원장의 직무)\n①위원장은 위원회를 대표하고 회의를 소집하며, 위원회의 업무를 총괄한다.\n②위원장이 부득이한 사유로 인하여 직무를 수행할 수 없을 때에는 위원장이 미리 지명한 위원이 그 직무를 대행한다.",
        "enforcement_date": "20260602",
        "relations": [],
        "images": [],
        "provision_id": "law:사행산업통합감독위원회법#JO0007"
      },
      {
        "article_no": "제8조",
        "article_title": "위원의 임기",
        "chapter": "",
        "content": "제8조(위원의 임기)\n①당연직 위원이 아닌 위원의 임기는 3년으로 하되, 1차에 한하여 연임할 수 있다.\n②당연직 위원이 아닌 위원의 결원이 생긴 경우에는 결원이 생긴 날부터 30일 이내에 보궐위원을 임명하거나 위촉하여야 하며, 보궐위원의 임기는 전임자의 남은 기간으로 한다.",
        "enforcement_date": "20260602",
        "relations": [],
        "images": [],
        "provision_id": "law:사행산업통합감독위원회법#JO0008"
      },
      {
        "article_no": "제9조",
        "article_title": "위원회의 심의ㆍ의결 등",
        "chapter": "",
        "content": "제9조(위원회의 심의ㆍ의결 등)\n①위원회는 재적위원 과반수의 출석과 출석위원 과반수의 찬성으로 심의ㆍ의결한다.\n②위원회는 업무를 효율적으로 수행하기 위하여 위원회에 분야별 분과위원회를 둘 수 있다.\n③그 밖에 위원회의 운영 등에 관하여 필요한 사항은 위원회규칙으로 정한다.",
        "enforcement_date": "20260602",
        "relations": [
          {
            "relation_type": "delegation",
            "delegation_type": "위임행정규칙",
            "target_category": "행정규칙",
            "source_article_no": "제9조",
            "source_clause": "제9조",
            "link_text": "위원회규칙으로 정한다",
            "line_text": "",
            "target_law_name": "사행산업통합감독위원회 운영규칙",
            "target_article_no": "",
            "target_article_title": "",
            "target_mst": "",
            "target_url": "https://www.law.go.kr/행정규칙/사행산업통합감독위원회 운영규칙",
            "resolve_method": "rendered_dom",
            "source_provision_id": "law:사행산업통합감독위원회법#JO0009",
            "reference_id": "admrul:사행산업통합감독위원회운영규칙#DOC"
          },
          {
            "relation_type": "delegation",
            "delegation_type": "위임행정규칙",
            "target_category": "행정규칙",
            "source_article_no": "제9조",
            "source_clause": "제9조제3항",
            "link_text": "위원회규칙으로 정한다",
            "line_text": "위원회의 운영 등에 관하여 필요한 사항은 위원회규칙으로 정한다.",
            "target_law_name": "사행산업통합감독위원회 운영규칙",
            "target_article_no": "",
            "target_article_title": "",
            "target_mst": "2100000264866",
            "target_url": "https://www.law.go.kr/행정규칙/사행산업통합감독위원회 운영규칙",
            "resolve_method": "lsDelegated+current",
            "superseded_target": {
              "target_law_name": "사행산업통합감독위원회 운영규칙",
              "target_mst": "2100000249958",
              "target_url": "https://www.law.go.kr/행정규칙/사행산업통합감독위원회 운영규칙"
            },
            "source_provision_id": "law:사행산업통합감독위원회법#JO0009",
            "reference_id": "admrul:사행산업통합감독위원회운영규칙#DOC"
          }
        ],
        "images": [],
        "provision_id": "law:사행산업통합감독위원회법#JO0009"
      },
      {
        "article_no": "제10조",
        "article_title": "위원의 결격 사유",
        "chapter": "",
        "content": "제10조(위원의 결격 사유)\n①다음 각 호의 어느 하나에 해당하는 자는 위원이 될 수 없다. <개정 2012.5.23>\n1.  대한민국 국민이 아닌 자\n2.  「정당법」에 따른 당원\n3.  「국가공무원법」 제33조 각 호의 어느 하나에 해당하는 자\n4.  사행산업사업자 또는 그 임직원\n②위원이 제1항 각 호의 어느 하나에 해당하게 된 경우에는 당연히 면직되거나 해촉된다.",
        "enforcement_date": "20260602",
        "relations": [
          {
            "relation_type": "citation",
            "delegation_type": null,
            "target_category": "법령",
            "source_article_no": "제10조",
            "source_clause": "제10조",
            "link_text": "「정당법」",
            "line_text": "",
            "target_law_name": "정당법",
            "target_article_no": "",
            "target_article_title": "",
            "target_mst": "257687",
            "target_url": "https://www.law.go.kr/법령/정당법",
            "resolve_method": "rendered_link",
            "source_provision_id": "law:사행산업통합감독위원회법#JO0010",
            "reference_id": "law:정당법#DOC"
          },
          {
            "relation_type": "citation",
            "delegation_type": null,
            "target_category": "법령",
            "source_article_no": "제10조",
            "source_clause": "제10조",
            "link_text": "「국가공무원법」",
            "line_text": "",
            "target_law_name": "국가공무원법",
            "target_article_no": "",
            "target_article_title": "",
            "target_mst": "286457",
            "target_url": "https://www.law.go.kr/법령/국가공무원법",
            "resolve_method": "rendered_link",
            "source_provision_id": "law:사행산업통합감독위원회법#JO0010",
            "reference_id": "law:국가공무원법#DOC"
          },
          {
            "relation_type": "citation",
            "delegation_type": null,
            "target_category": "법령",
            "source_article_no": "제10조",
            "source_clause": "제10조",
            "link_text": "제33조",
            "line_text": "",
            "target_law_name": "국가공무원법",
            "target_article_no": "제33조",
            "target_article_title": "결격사유",
            "target_mst": "286457",
            "target_url": "https://www.law.go.kr/법령/국가공무원법/제33조",
            "resolve_method": "rendered_link",
            "source_provision_id": "law:사행산업통합감독위원회법#JO0010",
            "reference_id": "law:국가공무원법#JO0033"
          }
        ],
        "images": [],
        "provision_id": "law:사행산업통합감독위원회법#JO0010"
      },
      {
        "article_no": "제11조",
        "article_title": "위원의 직무상 독립과 신분보장",
        "chapter": "",
        "content": "제11조(위원의 직무상 독립과 신분보장)\n①위원은 임기 중 직무와 관련하여 외부의 지시나 간섭을 받지 아니한다.\n②위원은 다음 각 호의 어느 하나에 해당하는 경우를 제외하고는 그의 의사에 반하여 면직되거나 신분상 불이익을 받지 아니한다.\n1.  제10조제1항의 결격 사유에 해당하게 된 경우\n2.  심신상의 장애로 인하여 직무를 수행할 수 없게 된 경우",
        "enforcement_date": "20260602",
        "relations": [
          {
            "relation_type": "internal_ref",
            "delegation_type": null,
            "target_category": "법령",
            "source_article_no": "제11조",
            "source_clause": "제11조",
            "link_text": "제10조",
            "line_text": "",
            "target_law_name": "사행산업통합감독위원회법",
            "target_article_no": "제10조",
            "target_article_title": "위원의 결격 사유",
            "target_mst": "",
            "target_url": "https://www.law.go.kr/법령/사행산업통합감독위원회법/제10조",
            "resolve_method": "rendered_link",
            "source_provision_id": "law:사행산업통합감독위원회법#JO0011",
            "reference_id": "law:사행산업통합감독위원회법#JO0010"
          },
          {
            "relation_type": "internal_ref",
            "delegation_type": null,
            "target_category": "법령",
            "source_article_no": "제11조",
            "source_clause": "제11조",
            "link_text": "제1항",
            "line_text": "",
            "target_law_name": "사행산업통합감독위원회법",
            "target_article_no": "제10조",
            "target_article_title": "위원의 결격 사유",
            "target_mst": "",
            "target_url": "https://www.law.go.kr/법령/사행산업통합감독위원회법/제10조",
            "resolve_method": "rendered_link",
            "source_provision_id": "law:사행산업통합감독위원회법#JO0011",
            "reference_id": "law:사행산업통합감독위원회법#JO0010"
          }
        ],
        "images": [],
        "provision_id": "law:사행산업통합감독위원회법#JO0011"
      },
      {
        "article_no": "제12조",
        "article_title": "전문위원",
        "chapter": "",
        "content": "제12조(전문위원)\n①위원장은 위원회의 업무를 효율적으로 지원하고 전문적인 조사ㆍ연구를 위하여 필요하다고 인정할 때에는 특수 분야의 전문가를 전문위원으로 둘 수 있다.\n②전문위원은 위원회의 의결을 거쳐 위원장이 임명하거나 위촉한다.\n③전문위원의 수, 자격 등에 관하여 필요한 사항은 대통령령으로 정한다.",
        "enforcement_date": "20260602",
        "relations": [
          {
            "relation_type": "delegation",
            "delegation_type": "시행령",
            "target_category": "법령",
            "source_article_no": "제12조",
            "source_clause": "제12조제3항",
            "link_text": "대통령령",
            "line_text": "대통령령으로 정한다",
            "target_law_name": "사행산업통합감독위원회법 시행령",
            "target_article_no": "제5조",
            "target_article_title": "전문위원의 수 등",
            "target_mst": "284761",
            "target_url": "https://www.law.go.kr/법령/사행산업통합감독위원회법 시행령/제5조",
            "resolve_method": "lsDelegated",
            "source_provision_id": "law:사행산업통합감독위원회법#JO0012",
            "reference_id": "law:사행산업통합감독위원회법시행령#JO0005"
          }
        ],
        "images": [],
        "provision_id": "law:사행산업통합감독위원회법#JO0012"
      },
      {
        "article_no": "제13조",
        "article_title": "사무처의 설치",
        "chapter": "",
        "content": "제13조(사무처의 설치)\n①위원회의 사무를 처리하기 위하여 위원회에 사무처를 둔다.\n②사무처에는 사무처장 1인과 그 밖에 필요한 직원을 둔다.\n③사무처장은 위원장의 지휘를 받아 위원회의 사무를 관장하고 소속 직원을 지휘하고 감독하며 위원회에 출석하여 발언할 수 있다.\n④그 밖에 사무처의 조직에 관하여 필요한 사항은 대통령령으로 정하고, 운영에 관하여 필요한 사항은 위원회규칙으로 정한다.",
        "enforcement_date": "20260602",
        "relations": [
          {
            "relation_type": "delegation",
            "delegation_type": "시행령",
            "target_category": "법령",
            "source_article_no": "제13조",
            "source_clause": "제13조제4항",
            "link_text": "대통령령",
            "line_text": "대통령령으로 정하고",
            "target_law_name": "사행산업통합감독위원회 사무처 직제",
            "target_article_no": "",
            "target_article_title": "모든조문",
            "target_mst": "145866",
            "target_url": "https://www.law.go.kr/법령/사행산업통합감독위원회 사무처 직제",
            "resolve_method": "lsDelegated",
            "source_provision_id": "law:사행산업통합감독위원회법#JO0013",
            "reference_id": "law:사행산업통합감독위원회사무처직제#DOC"
          }
        ],
        "images": [],
        "provision_id": "law:사행산업통합감독위원회법#JO0013"
      },
      {
        "article_no": "제14조",
        "article_title": "한국도박문제예방치유원",
        "chapter": "",
        "content": "제14조(한국도박문제예방치유원)\n① 사행산업 또는 불법사행산업으로 인한 중독 및 도박 문제 예방과 관련한 다음 각 호의 사업과 활동을 하기 위하여 한국도박문제예방치유원(이하 \"예방치유원\"이라 한다)을 설립한다. <개정 2019.11.26, 2022.1.18>\n1.  예방ㆍ치유를 위한 상담ㆍ교육ㆍ홍보 및 관련 프로그램의 개발ㆍ보급\n2.  조사ㆍ연구ㆍ분석 및 평가\n3.  예방ㆍ치유를 위한 전문인력 양성\n4.  전문 의료기관 등과의 연계ㆍ협력\n5.  예방사업 및 중독자 치유ㆍ재활 사업 지원\n6.  예방ㆍ치유 관련 국제 교류 및 협력\n7.  청소년의 도박 중독에 관한 조사 및 연구\n8.  정부 또는 위원회가 위탁하는 사업\n9.  그 밖에 사행산업이나 불법사행산업으로 인한 중독 및 도박 문제의 예방ㆍ치유를 위하여 필요한 사업 또는 활동\n② 예방치유원은 법인으로 한다. <개정 2022.1.18>\n③ 예방치유원에 임원으로서 이사장을 포함한 15명 이내의 이사와 감사 1명을 두며, 임원은 이사회에서 추천받아 위원장이 임면한다. 이 경우 임원의 임기 등 필요한 사항은 정관으로 정한다. <개정 2018.12.24, 2022.1.18>\n④ 예방치유원은 정관을 변경하려는 경우에는 위원장의 인가를 받아야 한다. <개정 2022.1.18>\n⑤ 정부와 위원회는 예방치유원에 대하여 필요한 경비를 예산의 범위에서 보조 또는 출연할 수 있다. <개정 2022.1.18>\n⑥ 예방치유원은 대통령령으로 정하는 바에 따라 매 사업연도 개시 전까지 사업계획 및 예산안을 작성ㆍ제출하여 위원회의 승인을 받아야 한다. 이를 변경하려는 경우에도 또한 같다. <개정 2022.1.18>\n⑦ 예방치유원은 필요한 경우 위원장의 승인을 받아 지역센터를 설치ㆍ운영할 수 있다. <개정 2022.1.18>\n⑧ 예방치유원이 아닌 자는 한국도박문제예방치유원 또는 이와 유사한 명칭을 사용하여서는 아니 된다. <개정 2022.1.18>\n⑨ 예방치유원에 관하여 이 법에서 정한 것 외에는 「민법」 중 재단법인에 관한 규정을 준용한다. <개정 2022.1.18>",
        "enforcement_date": "20260602",
        "relations": [
          {
            "relation_type": "citation",
            "delegation_type": null,
            "target_category": "법령",
            "source_article_no": "제14조",
            "source_clause": "제14조",
            "link_text": "「민법」",
            "line_text": "",
            "target_law_name": "민법",
            "target_article_no": "",
            "target_article_title": "",
            "target_mst": "284415",
            "target_url": "https://www.law.go.kr/법령/민법",
            "resolve_method": "rendered_link",
            "source_provision_id": "law:사행산업통합감독위원회법#JO0014",
            "reference_id": "law:민법#DOC"
          },
          {
            "relation_type": "delegation",
            "delegation_type": "위임학칙공단",
            "target_category": "학칙공단",
            "source_article_no": "제14조",
            "source_clause": "제14조",
            "link_text": "정관으로 정한다.",
            "line_text": "",
            "target_law_name": "한국도박문제예방치유원 정관",
            "target_article_no": "",
            "target_article_title": "",
            "target_mst": "",
            "target_url": "https://www.law.go.kr/학칙공단/한국도박문제예방치유원 정관",
            "resolve_method": "rendered_dom",
            "source_provision_id": "law:사행산업통합감독위원회법#JO0014",
            "reference_id": "pi:한국도박문제예방치유원정관#DOC"
          },
          {
            "relation_type": "delegation",
            "delegation_type": "위임학칙공단",
            "target_category": "학칙공단",
            "source_article_no": "제14조",
            "source_clause": "제14조제3항",
            "link_text": "정관으로 정한다.",
            "line_text": "③ 예방치유원에 임원으로서 이사장을 포함한 15명 이내의 이사와 감사 1명을 두며, 임원은 이사회에서 추천받아 위원장이 임면한다. 이 경우 임원의 임기 등 필요한 사항은 정관으로 정한다.",
            "target_law_name": "한국도박문제관리센터 정관",
            "target_article_no": "",
            "target_article_title": "",
            "target_mst": "2200000088653",
            "target_url": "https://www.law.go.kr/학칙공단/한국도박문제관리센터 정관",
            "resolve_method": "lsDelegated",
            "is_current_target": false,
            "source_provision_id": "law:사행산업통합감독위원회법#JO0014",
            "reference_id": "pi:한국도박문제관리센터정관#DOC"
          },
          {
            "relation_type": "delegation",
            "delegation_type": "시행령",
            "target_category": "법령",
            "source_article_no": "제14조",
            "source_clause": "제14조제6항",
            "link_text": "대통령령",
            "line_text": "대통령령으로 정하는",
            "target_law_name": "사행산업통합감독위원회법 시행령",
            "target_article_no": "제8조",
            "target_article_title": "한국도박문제예방치유원의 사업계획 및 예산안의 제출",
            "target_mst": "284761",
            "target_url": "https://www.law.go.kr/법령/사행산업통합감독위원회법 시행령/제8조",
            "resolve_method": "lsDelegated",
            "source_provision_id": "law:사행산업통합감독위원회법#JO0014",
            "reference_id": "law:사행산업통합감독위원회법시행령#JO0008"
          }
        ],
        "images": [],
        "provision_id": "law:사행산업통합감독위원회법#JO0014"
      },
      {
        "article_no": "제14조의2",
        "article_title": "중독예방치유부담금의 부과ㆍ징수 등",
        "chapter": "",
        "content": "제14조의2(중독예방치유부담금의 부과ㆍ징수 등)\n① 위원회는 사행산업 또는 불법사행산업으로 인한 중독 및 도박 문제의 예방ㆍ치유와 예방치유원의 운영을 위하여 사행산업사업자에게 연간 순매출액(총매출액에서 환급금 등을 공제한 금액으로서 대통령령으로 정하는 금액을 말한다)의 1만분의 35 이상 1만분의 50 이하의 범위에서 대통령령으로 정하는 비율에 해당하는 중독예방치유부담금(이하 \"부담금\"이라 한다)을 부과ㆍ징수할 수 있다. 다만, 「석탄산업전환지역 개발 지원에 관한 특별법」에 따른 카지노사업자를 제외한 「관광진흥법」에 따른 카지노사업자에게는 부담금을 부과하지 아니한다. <개정 2022.1.18, 2023.6.20, 2025.12.30>\n② 위원회는 부담금을 부과할 때 사행산업사업자의 수익성, 제5조제1항제7호에 따른 건전화 평가 및 제16조제1항제1호에 따른 총량 준수 결과 등을 고려하여 사행산업사업자별로 부담금의 부과 비율을 다르게 정할 수 있다. 이 경우 제1항에도 불구하고 수익성이 열악하거나 건전화 평가가 우수한 사행산업사업자 등에 대해서는 대통령령으로 정하는 바에 따라 1만분의 35 미만의 비율을 정하여 부과할 수 있다. <신설 2023.6.20>\n③ 위원회는 부담금의 부과금액을 전년도 매출을 기준으로 산정하여 매년 5월 31일까지 사행산업사업자에게 통지(전자통지를 포함한다. 이하 같다)하여야 한다. <개정 2023.6.20>\n④ 위원회는 부담금이 대통령령으로 정하는 기준을 초과하는 경우에는 대통령령으로 정하는 바에 따라 분할하여 납부하게 할 수 있다. <신설 2018.10.16, 2023.6.20>\n⑤ 위원회는 부담금을 납부하여야 할 자가 납부기한까지 납부하지 아니한 경우에는 납부기한 경과 후 15일 이내에 독촉장을 발부하여야 한다. 이 경우 납부기한은 독촉장의 발부일부터 10일 이내로 한다. <개정 2018.10.16, 2023.6.20>\n⑥ 위원회는 제5항에 따라 독촉받은 자가 정하여진 납부기한까지 부담금을 납부하지 아니한 경우에는 그 납부기한의 다음 날부터 납부일의 전일까지의 기간에 대하여 그 체납된 금액의 100분의 3을 초과하지 아니하는 범위에서 대통령령으로 정하는 가산금을 부과ㆍ징수할 수 있다. <개정 2018.10.16, 2023.6.20>\n⑦ 위원회는 사행산업사업자가 제5항에 따른 부담금 또는 제6항에 따른 가산금을 납부하지 아니한 경우에는 국세 체납처분의 예에 따라 이를 징수할 수 있다. <개정 2018.10.16, 2023.6.20>\n⑧ 위원회는 부담금 및 가산금의 부과ㆍ징수를 예방치유원에 위탁할 수 있다. <개정 2017.12.19, 2018.10.16, 2022.1.18, 2023.6.20>\n⑨ 위원회는 부담금 및 가산금을 사행산업중독예방치유계정으로 납입하여야 한다. <신설 2017.12.19, 2018.10.16, 2023.6.20>\n⑩ 부담금을 부과받은 사행산업사업자가 부과받은 사항에 대하여 이의가 있는 경우에는 제3항에 따른 통지를 받은 날부터 30일 이내에 위원회에 이의신청을 할 수 있다. 이 경우 위원회는 이의신청을 받은 날부터 60일 이내에 위원회의 의결을 거쳐 그 결과를 신청인에게 통지하여야 한다. <신설 2026.6.2>\n⑪ 제10항에서 규정한 사항 외에 이의신청에 관한 사항은 「행정기본법」 제36조(같은 조 제2항 단서는 제외한다)에 따른다. <신설 2026.6.2>\n⑫ 그 밖에 부담금의 부과ㆍ징수의 방법 및 절차 등에 필요한 사항은 대통령령으로 정한다. <개정 2017.12.19, 2018.10.16, 2023.6.20, 2026.6.2>",
        "enforcement_date": "20260602",
        "relations": [
          {
            "relation_type": "citation",
            "delegation_type": null,
            "target_category": "법령",
            "source_article_no": "제14조의2",
            "source_clause": "제14조의2",
            "link_text": "「석탄산업전환지역 개발 지원에 관한 특별법」",
            "line_text": "",
            "target_law_name": "석탄산업전환지역개발지원에관한특별법",
            "target_article_no": "",
            "target_article_title": "",
            "target_mst": "281897",
            "target_url": "https://www.law.go.kr/법령/석탄산업전환지역개발지원에관한특별법",
            "resolve_method": "rendered_link",
            "source_provision_id": "law:사행산업통합감독위원회법#JO0014_02",
            "reference_id": "law:석탄산업전환지역개발지원에관한특별법#DOC"
          },
          {
            "relation_type": "citation",
            "delegation_type": null,
            "target_category": "법령",
            "source_article_no": "제14조의2",
            "source_clause": "제14조의2",
            "link_text": "「관광진흥법」",
            "line_text": "",
            "target_law_name": "관광진흥법",
            "target_article_no": "",
            "target_article_title": "",
            "target_mst": "279659",
            "target_url": "https://www.law.go.kr/법령/관광진흥법",
            "resolve_method": "rendered_link",
            "source_provision_id": "law:사행산업통합감독위원회법#JO0014_02",
            "reference_id": "law:관광진흥법#DOC"
          },
          {
            "relation_type": "internal_ref",
            "delegation_type": null,
            "target_category": "법령",
            "source_article_no": "제14조의2",
            "source_clause": "제14조의2",
            "link_text": "제5조",
            "line_text": "",
            "target_law_name": "사행산업통합감독위원회법",
            "target_article_no": "제5조",
            "target_article_title": "위원회의 기능",
            "target_mst": "",
            "target_url": "https://www.law.go.kr/법령/사행산업통합감독위원회법/제5조",
            "resolve_method": "rendered_link",
            "source_provision_id": "law:사행산업통합감독위원회법#JO0014_02",
            "reference_id": "law:사행산업통합감독위원회법#JO0005"
          },
          {
            "relation_type": "internal_ref",
            "delegation_type": null,
            "target_category": "법령",
            "source_article_no": "제14조의2",
            "source_clause": "제14조의2",
            "link_text": "제1항",
            "line_text": "",
            "target_law_name": "사행산업통합감독위원회법",
            "target_article_no": "제5조",
            "target_article_title": "위원회의 기능",
            "target_mst": "",
            "target_url": "https://www.law.go.kr/법령/사행산업통합감독위원회법/제5조",
            "resolve_method": "rendered_link",
            "source_provision_id": "law:사행산업통합감독위원회법#JO0014_02",
            "reference_id": "law:사행산업통합감독위원회법#JO0005"
          },
          {
            "relation_type": "internal_ref",
            "delegation_type": null,
            "target_category": "법령",
            "source_article_no": "제14조의2",
            "source_clause": "제14조의2",
            "link_text": "제7호",
            "line_text": "",
            "target_law_name": "사행산업통합감독위원회법",
            "target_article_no": "제5조",
            "target_article_title": "위원회의 기능",
            "target_mst": "",
            "target_url": "https://www.law.go.kr/법령/사행산업통합감독위원회법/제5조",
            "resolve_method": "rendered_link",
            "source_provision_id": "law:사행산업통합감독위원회법#JO0014_02",
            "reference_id": "law:사행산업통합감독위원회법#JO0005"
          },
          {
            "relation_type": "internal_ref",
            "delegation_type": null,
            "target_category": "법령",
            "source_article_no": "제14조의2",
            "source_clause": "제14조의2",
            "link_text": "제16조",
            "line_text": "",
            "target_law_name": "사행산업통합감독위원회법",
            "target_article_no": "제16조",
            "target_article_title": "종합계획의 수립 등",
            "target_mst": "",
            "target_url": "https://www.law.go.kr/법령/사행산업통합감독위원회법/제16조",
            "resolve_method": "rendered_link",
            "source_provision_id": "law:사행산업통합감독위원회법#JO0014_02",
            "reference_id": "law:사행산업통합감독위원회법#JO0016"
          },
          {
            "relation_type": "internal_ref",
            "delegation_type": null,
            "target_category": "법령",
            "source_article_no": "제14조의2",
            "source_clause": "제14조의2",
            "link_text": "제1항",
            "line_text": "",
            "target_law_name": "사행산업통합감독위원회법",
            "target_article_no": "제16조",
            "target_article_title": "종합계획의 수립 등",
            "target_mst": "",
            "target_url": "https://www.law.go.kr/법령/사행산업통합감독위원회법/제16조",
            "resolve_method": "rendered_link",
            "source_provision_id": "law:사행산업통합감독위원회법#JO0014_02",
            "reference_id": "law:사행산업통합감독위원회법#JO0016"
          },
          {
            "relation_type": "internal_ref",
            "delegation_type": null,
            "target_category": "법령",
            "source_article_no": "제14조의2",
            "source_clause": "제14조의2",
            "link_text": "제1호",
            "line_text": "",
            "target_law_name": "사행산업통합감독위원회법",
            "target_article_no": "제16조",
            "target_article_title": "종합계획의 수립 등",
            "target_mst": "",
            "target_url": "https://www.law.go.kr/법령/사행산업통합감독위원회법/제16조",
            "resolve_method": "rendered_link",
            "source_provision_id": "law:사행산업통합감독위원회법#JO0014_02",
            "reference_id": "law:사행산업통합감독위원회법#JO0016"
          },
          {
            "relation_type": "citation",
            "delegation_type": null,
            "target_category": "법령",
            "source_article_no": "제14조의2",
            "source_clause": "제14조의2",
            "link_text": "「행정기본법」",
            "line_text": "",
            "target_law_name": "행정기본법",
            "target_article_no": "",
            "target_article_title": "",
            "target_mst": "269955",
            "target_url": "https://www.law.go.kr/법령/행정기본법",
            "resolve_method": "rendered_link",
            "source_provision_id": "law:사행산업통합감독위원회법#JO0014_02",
            "reference_id": "law:행정기본법#DOC"
          },
          {
            "relation_type": "citation",
            "delegation_type": null,
            "target_category": "법령",
            "source_article_no": "제14조의2",
            "source_clause": "제14조의2",
            "link_text": "제36조",
            "line_text": "",
            "target_law_name": "행정기본법",
            "target_article_no": "제36조",
            "target_article_title": "처분에 대한 이의신청",
            "target_mst": "269955",
            "target_url": "https://www.law.go.kr/법령/행정기본법/제36조",
            "resolve_method": "rendered_link",
            "source_provision_id": "law:사행산업통합감독위원회법#JO0014_02",
            "reference_id": "law:행정기본법#JO0036"
          },
          {
            "relation_type": "citation",
            "delegation_type": null,
            "target_category": "법령",
            "source_article_no": "제14조의2",
            "source_clause": "제14조의2",
            "link_text": "같은 조",
            "line_text": "",
            "target_law_name": "행정기본법",
            "target_article_no": "제36조",
            "target_article_title": "처분에 대한 이의신청",
            "target_mst": "269955",
            "target_url": "https://www.law.go.kr/법령/행정기본법/제36조",
            "resolve_method": "rendered_link",
            "source_provision_id": "law:사행산업통합감독위원회법#JO0014_02",
            "reference_id": "law:행정기본법#JO0036"
          },
          {
            "relation_type": "citation",
            "delegation_type": null,
            "target_category": "법령",
            "source_article_no": "제14조의2",
            "source_clause": "제14조의2",
            "link_text": "제2항",
            "line_text": "",
            "target_law_name": "행정기본법",
            "target_article_no": "제36조",
            "target_article_title": "처분에 대한 이의신청",
            "target_mst": "269955",
            "target_url": "https://www.law.go.kr/법령/행정기본법/제36조",
            "resolve_method": "rendered_link",
            "source_provision_id": "law:사행산업통합감독위원회법#JO0014_02",
            "reference_id": "law:행정기본법#JO0036"
          },
          {
            "relation_type": "delegation",
            "delegation_type": "시행령",
            "target_category": "법령",
            "source_article_no": "제14조의2",
            "source_clause": "제14조의2제1항",
            "link_text": "대통령령",
            "line_text": "대통령령으로 정하는 비율",
            "target_law_name": "사행산업통합감독위원회법 시행령",
            "target_article_no": "제9조",
            "target_article_title": "중독예방치유부담금의 산정방법 등",
            "target_mst": "284761",
            "target_url": "https://www.law.go.kr/법령/사행산업통합감독위원회법 시행령/제9조",
            "resolve_method": "lsDelegated",
            "source_provision_id": "law:사행산업통합감독위원회법#JO0014_02",
            "reference_id": "law:사행산업통합감독위원회법시행령#JO0009"
          },
          {
            "relation_type": "delegation",
            "delegation_type": "시행령",
            "target_category": "법령",
            "source_article_no": "제14조의2",
            "source_clause": "제14조의2제1항",
            "link_text": "대통령령",
            "line_text": "대통령령으로 정하는 금액",
            "target_law_name": "사행산업통합감독위원회법 시행령",
            "target_article_no": "제9조",
            "target_article_title": "중독예방치유부담금의 산정방법 등",
            "target_mst": "284761",
            "target_url": "https://www.law.go.kr/법령/사행산업통합감독위원회법 시행령/제9조",
            "resolve_method": "lsDelegated",
            "source_provision_id": "law:사행산업통합감독위원회법#JO0014_02",
            "reference_id": "law:사행산업통합감독위원회법시행령#JO0009"
          },
          {
            "relation_type": "delegation",
            "delegation_type": "시행령",
            "target_category": "법령",
            "source_article_no": "제14조의2",
            "source_clause": "제14조의2제2항",
            "link_text": "대통령령",
            "line_text": "대통령령으로 정하는",
            "target_law_name": "사행산업통합감독위원회법 시행령",
            "target_article_no": "제9조",
            "target_article_title": "중독예방치유부담금의 산정방법 등",
            "target_mst": "284761",
            "target_url": "https://www.law.go.kr/법령/사행산업통합감독위원회법 시행령/제9조",
            "resolve_method": "lsDelegated",
            "source_provision_id": "law:사행산업통합감독위원회법#JO0014_02",
            "reference_id": "law:사행산업통합감독위원회법시행령#JO0009"
          },
          {
            "relation_type": "delegation",
            "delegation_type": "시행령",
            "target_category": "법령",
            "source_article_no": "제14조의2",
            "source_clause": "제14조의2제4항",
            "link_text": "대통령령",
            "line_text": "대통령령으로 정하는 기준을",
            "target_law_name": "사행산업통합감독위원회법 시행령",
            "target_article_no": "제9조",
            "target_article_title": "중독예방치유부담금의 산정방법 등",
            "target_mst": "284761",
            "target_url": "https://www.law.go.kr/법령/사행산업통합감독위원회법 시행령/제9조",
            "resolve_method": "lsDelegated",
            "source_provision_id": "law:사행산업통합감독위원회법#JO0014_02",
            "reference_id": "law:사행산업통합감독위원회법시행령#JO0009"
          },
          {
            "relation_type": "delegation",
            "delegation_type": "시행령",
            "target_category": "법령",
            "source_article_no": "제14조의2",
            "source_clause": "제14조의2제4항",
            "link_text": "대통령령",
            "line_text": "대통령령으로 정하는 바에",
            "target_law_name": "사행산업통합감독위원회법 시행령",
            "target_article_no": "제9조",
            "target_article_title": "중독예방치유부담금의 산정방법 등",
            "target_mst": "284761",
            "target_url": "https://www.law.go.kr/법령/사행산업통합감독위원회법 시행령/제9조",
            "resolve_method": "lsDelegated",
            "source_provision_id": "law:사행산업통합감독위원회법#JO0014_02",
            "reference_id": "law:사행산업통합감독위원회법시행령#JO0009"
          },
          {
            "relation_type": "delegation",
            "delegation_type": "시행령",
            "target_category": "법령",
            "source_article_no": "제14조의2",
            "source_clause": "제14조의2제6항",
            "link_text": "대통령령",
            "line_text": "대통령령으로 정하는",
            "target_law_name": "사행산업통합감독위원회법 시행령",
            "target_article_no": "제10조",
            "target_article_title": "가산금",
            "target_mst": "284761",
            "target_url": "https://www.law.go.kr/법령/사행산업통합감독위원회법 시행령/제10조",
            "resolve_method": "lsDelegated",
            "source_provision_id": "law:사행산업통합감독위원회법#JO0014_02",
            "reference_id": "law:사행산업통합감독위원회법시행령#JO0010"
          },
          {
            "relation_type": "delegation",
            "delegation_type": "시행령",
            "target_category": "법령",
            "source_article_no": "제14조의2",
            "source_clause": "제14조의2제12항",
            "link_text": "대통령령",
            "line_text": "대통령령으로 정한다",
            "target_law_name": "사행산업통합감독위원회법 시행령",
            "target_article_no": "제9조",
            "target_article_title": "중독예방치유부담금의 산정방법 등",
            "target_mst": "284761",
            "target_url": "https://www.law.go.kr/법령/사행산업통합감독위원회법 시행령/제9조",
            "resolve_method": "lsDelegated",
            "source_provision_id": "law:사행산업통합감독위원회법#JO0014_02",
            "reference_id": "law:사행산업통합감독위원회법시행령#JO0009"
          }
        ],
        "images": [],
        "provision_id": "law:사행산업통합감독위원회법#JO0014_02"
      },
      {
        "article_no": "제14조의3",
        "article_title": "국고보조",
        "chapter": "",
        "content": "제14조의3(국고보조) 정부는 사행산업 및 불법사행산업으로 인한 중독 및 도박 문제의 예방ㆍ치유와 관련한 사업 또는 활동이나 시설에 드는 경비의 일부를 예산의 범위에서 보조할 수 있다.",
        "enforcement_date": "20260602",
        "relations": [],
        "images": [],
        "provision_id": "law:사행산업통합감독위원회법#JO0014_03"
      },
      {
        "article_no": "제14조의4",
        "article_title": "국민체육진흥기금 내 사행산업중독예방치유계정의 재원 및 용도 등",
        "chapter": "",
        "content": "제14조의4(국민체육진흥기금 내 사행산업중독예방치유계정의 재원 및 용도 등)\n① 사행산업중독예방치유계정의 재원은 다음 각 호와 같다.\n1.  제14조의2에 따른 부담금 및 가산금\n2.  정부가 아닌 자의 출연금 및 기부금(「기부금품의 모집 및 사용에 관한 법률」에 따른 자발적 기탁금품에 한정한다)\n3.  사행산업중독예방치유계정의 운용으로 생기는 수익금\n4.  「공공자금관리기금법」에 따른 공공자금관리기금으로부터의 예수금(豫受金)\n5.  그 밖에 대통령령으로 정하는 수익금\n② 사행산업중독예방치유계정은 사행산업 또는 불법사행산업으로 인한 중독 및 도박 문제의 예방ㆍ치유와 예방치유원의 운영 등을 위하여 사용한다. <개정 2022.1.18>\n③ 위원회는 사행산업중독예방치유계정의 관리ㆍ운용을 예방치유원에 위탁할 수 있다. <개정 2022.1.18>",
        "enforcement_date": "20260602",
        "relations": [
          {
            "relation_type": "internal_ref",
            "delegation_type": null,
            "target_category": "법령",
            "source_article_no": "제14조의4",
            "source_clause": "제14조의4",
            "link_text": "제14조의2",
            "line_text": "",
            "target_law_name": "사행산업통합감독위원회법",
            "target_article_no": "제14조의2",
            "target_article_title": "중독예방치유부담금의 부과ㆍ징수 등",
            "target_mst": "",
            "target_url": "https://www.law.go.kr/법령/사행산업통합감독위원회법/제14조의2",
            "resolve_method": "rendered_link",
            "source_provision_id": "law:사행산업통합감독위원회법#JO0014_04",
            "reference_id": "law:사행산업통합감독위원회법#JO0014_02"
          },
          {
            "relation_type": "citation",
            "delegation_type": null,
            "target_category": "법령",
            "source_article_no": "제14조의4",
            "source_clause": "제14조의4",
            "link_text": "「기부금품의 모집 및 사용에 관한 법률」",
            "line_text": "",
            "target_law_name": "기부금품의모집ㆍ사용및기부문화활성화에관한법률",
            "target_article_no": "",
            "target_article_title": "",
            "target_mst": "260853",
            "target_url": "https://www.law.go.kr/법령/기부금품의모집ㆍ사용및기부문화활성화에관한법률",
            "resolve_method": "rendered_link",
            "source_provision_id": "law:사행산업통합감독위원회법#JO0014_04",
            "reference_id": "law:기부금품의모집사용및기부문화활성화에관한법률#DOC"
          },
          {
            "relation_type": "citation",
            "delegation_type": null,
            "target_category": "법령",
            "source_article_no": "제14조의4",
            "source_clause": "제14조의4",
            "link_text": "「공공자금관리기금법」",
            "line_text": "",
            "target_law_name": "공공자금관리기금법",
            "target_article_no": "",
            "target_article_title": "",
            "target_mst": "276059",
            "target_url": "https://www.law.go.kr/법령/공공자금관리기금법",
            "resolve_method": "rendered_link",
            "source_provision_id": "law:사행산업통합감독위원회법#JO0014_04",
            "reference_id": "law:공공자금관리기금법#DOC"
          },
          {
            "relation_type": "citation",
            "delegation_type": null,
            "target_category": "법령",
            "source_article_no": "제14조의4",
            "source_clause": "제14조의4제1항제2호",
            "link_text": "「기부금품의 모집 및 사용에 관한 법률」",
            "line_text": "2.  정부가 아닌 자의 출연금 및 기부금(「기부금품의 모집 및 사용에 관한 법률」에 따른 자발적 기탁금품에 한정한다)",
            "target_law_name": "기부금품의 모집 및 사용에 관한 법률",
            "target_article_no": "",
            "target_article_title": "",
            "target_mst": "",
            "target_url": "https://www.law.go.kr/법령/기부금품의 모집 및 사용에 관한 법률",
            "resolve_method": "text_parse",
            "source_provision_id": "law:사행산업통합감독위원회법#JO0014_04",
            "reference_id": "law:기부금품의모집및사용에관한법률#DOC"
          }
        ],
        "images": [],
        "provision_id": "law:사행산업통합감독위원회법#JO0014_04"
      },
      {
        "article_no": "제15조",
        "article_title": "공무원 등의 파견과 채용",
        "chapter": "",
        "content": "제15조(공무원 등의 파견과 채용)\n①위원장은 사무처의 효율적인 운영을 위하여 필요하다고 인정하는 경우에는 관련 행정기관과 사행산업 관련 법인ㆍ단체의 장에게 공무원이나 법인ㆍ단체의 임직원의 파견을 요청할 수 있다.\n②제1항의 규정에 따라 요청을 받은 관련 행정기관과 사행산업 관련 법인ㆍ단체의 장은 특별한 사유가 없는 한 이에 응하여야 한다.\n③위원장은 중독예방ㆍ치유 등과 관련한 특수 전문 분야의 업무 수행을 위하여 「국가공무원법」 제26조의5에 따른 임기제공무원을 채용할 수 있다. <개정 2012.12.11>\n④제1항과 제3항의 규정에 따라 파견되거나 채용된 자는 그 복무에 관하여 위원장의 지휘와 감독을 받는다.",
        "enforcement_date": "20260602",
        "relations": [
          {
            "relation_type": "citation",
            "delegation_type": null,
            "target_category": "법령",
            "source_article_no": "제15조",
            "source_clause": "제15조",
            "link_text": "「국가공무원법」",
            "line_text": "",
            "target_law_name": "국가공무원법",
            "target_article_no": "",
            "target_article_title": "",
            "target_mst": "286457",
            "target_url": "https://www.law.go.kr/법령/국가공무원법",
            "resolve_method": "rendered_link",
            "source_provision_id": "law:사행산업통합감독위원회법#JO0015",
            "reference_id": "law:국가공무원법#DOC"
          },
          {
            "relation_type": "citation",
            "delegation_type": null,
            "target_category": "법령",
            "source_article_no": "제15조",
            "source_clause": "제15조",
            "link_text": "제26조의5",
            "line_text": "",
            "target_law_name": "국가공무원법",
            "target_article_no": "제26조의5",
            "target_article_title": "근무기간을 정하여 임용하는 공무원",
            "target_mst": "286457",
            "target_url": "https://www.law.go.kr/법령/국가공무원법/제26조의5",
            "resolve_method": "rendered_link",
            "source_provision_id": "law:사행산업통합감독위원회법#JO0015",
            "reference_id": "law:국가공무원법#JO0026_05"
          }
        ],
        "images": [],
        "provision_id": "law:사행산업통합감독위원회법#JO0015"
      },
      {
        "article_no": "제16조",
        "article_title": "종합계획의 수립 등",
        "chapter": "",
        "content": "제16조(종합계획의 수립 등)\n① 위원회는 사행산업의 통합적인 관리ㆍ감독 및 건전화와 불법사행산업의 근절을 위하여 다음 각 호의 사항을 포함하는 종합계획(이하 \"종합계획\"이라 한다)을 수립하여 시행하여야 한다. <개정 2012.5.23, 2019.11.26>\n1.  사행산업 업종 간의 통합 또는 개별 사행산업 업종의 영업장의 수, 매출액 규모 등에 관한 총량의 적용ㆍ조정과 관리ㆍ감독에 대한 단기 운영 계획과 중장기 운영 계획\n2.  사행산업 업종별 투명성과 건전성 확보 방안\n3.  사행산업 및 불법사행산업으로 인한 사회적 부작용 해소대책\n4.  사행산업사업자의 과도한 사행심 유발에 대한 현장 확인과 지도ㆍ감독 및 의무이행의 확보 방안\n5.  사행산업의 건전한 발전을 위한 광고ㆍ선전 및 과도한 사행심 해소 대책\n6.  불법사행산업의 효율적인 감시 방안 및 근절 대책\n7.  사행산업으로부터의 청소년 보호 대책\n8.  그 밖에 위원회의 의결로 결정한 사항\n② 위원회가 종합계획을 수립할 때에는 기획예산처ㆍ문화체육관광부ㆍ농림축산식품부 등 관계 행정기관으로부터 사행산업 업종별 단기 방안과 중장기 방안을 제출받아야 한다. <개정 2012.5.23, 2013.3.23, 2025.10.1>\n③위원회는 종합계획의 수립을 위하여 사행산업사업자 또는 관련 행정기관의 장 등에게 자료를 요청할 수 있으며 종합계획의 이행 여부의 확인을 위한 실태조사 등 필요한 조치를 할 수 있다.",
        "enforcement_date": "20260602",
        "relations": [],
        "images": [],
        "provision_id": "law:사행산업통합감독위원회법#JO0016"
      },
      {
        "article_no": "제17조",
        "article_title": "협의ㆍ조정 또는 권고 등",
        "chapter": "",
        "content": "제17조(협의ㆍ조정 또는 권고 등)\n①위원회는 제5조제1항제2호의 규정에 따른 사행산업 업종 간의 통합 또는 개별 사행산업 업종의 영업장의 수, 매출액 규모 등에 관한 총량의 적용 또는 조정이 필요하거나 관련 기관ㆍ단체 또는 개별 업계 등의 요청이 있을 경우 기획예산처ㆍ문화체육관광부ㆍ농림축산식품부 등의 관련 행정기관의 장과 협의하여 이를 적용 또는 조정하거나 권고할 수 있다. <개정 2008.2.29, 2012.5.23, 2013.3.23, 2025.10.1>\n②위원회는 과도한 사행심의 조장을 방지하기 위하여 경마, 경륜ㆍ경정, 복권, 체육진흥투표권 및 소싸움경기의 단위투표금액 조정에 관하여 관련 행정기관의 장에게 권고할 수 있다. <개정 2012.5.23>\n③제1항 및 제2항의 규정에 따라 협의ㆍ조정된 내용에 대하여 관련 행정기관의 장은 특별한 사유가 없는 한 이를 성실히 이행하여야 하며 권고를 받은 관련 행정기관의 장은 그 권고 사항을 존중하고 이행하기 위하여 노력하여야 한다.\n④ 제1항 및 제2항에 따라 권고를 받은 관련 행정기관의 장은 권고를 받은 날부터 90일 이내에 그 권고사항의 이행계획을 위원회에 통지하여야 한다. <신설 2018.10.16>\n⑤ 제1항 및 제2항에 따라 권고를 받은 관련 행정기관의 장은 그 권고의 내용을 이행하지 아니할 경우에는 그 이유를 위원회에 통보하여야 한다. <신설 2018.10.16>\n⑥ 위원회는 필요하다고 인정하면 제1항 및 제2항에 따른 위원회의 권고 및 제5항에 따라 권고를 받은 관련 행정기관의 장이 통보한 내용을 공표할 수 있다. <신설 2018.10.16>",
        "enforcement_date": "20260602",
        "relations": [
          {
            "relation_type": "internal_ref",
            "delegation_type": null,
            "target_category": "법령",
            "source_article_no": "제17조",
            "source_clause": "제17조",
            "link_text": "제5조",
            "line_text": "",
            "target_law_name": "사행산업통합감독위원회법",
            "target_article_no": "제5조",
            "target_article_title": "위원회의 기능",
            "target_mst": "",
            "target_url": "https://www.law.go.kr/법령/사행산업통합감독위원회법/제5조",
            "resolve_method": "rendered_link",
            "source_provision_id": "law:사행산업통합감독위원회법#JO0017",
            "reference_id": "law:사행산업통합감독위원회법#JO0005"
          },
          {
            "relation_type": "internal_ref",
            "delegation_type": null,
            "target_category": "법령",
            "source_article_no": "제17조",
            "source_clause": "제17조",
            "link_text": "제1항",
            "line_text": "",
            "target_law_name": "사행산업통합감독위원회법",
            "target_article_no": "제5조",
            "target_article_title": "위원회의 기능",
            "target_mst": "",
            "target_url": "https://www.law.go.kr/법령/사행산업통합감독위원회법/제5조",
            "resolve_method": "rendered_link",
            "source_provision_id": "law:사행산업통합감독위원회법#JO0017",
            "reference_id": "law:사행산업통합감독위원회법#JO0005"
          },
          {
            "relation_type": "internal_ref",
            "delegation_type": null,
            "target_category": "법령",
            "source_article_no": "제17조",
            "source_clause": "제17조",
            "link_text": "제2호",
            "line_text": "",
            "target_law_name": "사행산업통합감독위원회법",
            "target_article_no": "제5조",
            "target_article_title": "위원회의 기능",
            "target_mst": "",
            "target_url": "https://www.law.go.kr/법령/사행산업통합감독위원회법/제5조",
            "resolve_method": "rendered_link",
            "source_provision_id": "law:사행산업통합감독위원회법#JO0017",
            "reference_id": "law:사행산업통합감독위원회법#JO0005"
          }
        ],
        "images": [],
        "provision_id": "law:사행산업통합감독위원회법#JO0017"
      },
      {
        "article_no": "제18조",
        "article_title": "현장 확인 및 지도ㆍ감독 등",
        "chapter": "",
        "content": "제18조(현장 확인 및 지도ㆍ감독 등)\n①위원회는 사행산업의 과도한 사행심 유발 방지를 위하여 다음 각 호의 사항에 관하여 현장을 확인하고 지도ㆍ감독한다. <개정 2012.5.23>\n1.  과도한 사행심을 유발하는 광고 또는 선전행위\n2.  사행산업의 영업장 안 또는 주변에서 이루어지는 과도한 사행심을 조장하는 금융거래행위\n3.  사행산업사업자의 준수사항 이행 여부\n4.  그 밖에 과도한 사행심을 유발하는 영업 행위로서 대통령령이 정하는 사항\n②위원회는 제1항의 규정에 따른 현장 확인과 지도ㆍ감독을 위하여 필요한 경우 사행산업사업자가 운영하는 사무소 또는 영업장에 위원회의 소속 직원을 파견하거나 사무소 또는 영업장을 출입하여 장부ㆍ서류 그 밖의 자료나 물건을 조사하게 할 수 있으며, 필요한 경우 소관 행정기관에 조사를 의뢰할 수 있다.\n③제2항의 규정에 따라 조사를 하는 소속 직원은 그 권한을 표시하는 증표를 지니고 이를 관계인에게 내보여야 한다.",
        "enforcement_date": "20260602",
        "relations": [
          {
            "relation_type": "delegation",
            "delegation_type": "시행령",
            "target_category": "법령",
            "source_article_no": "제18조",
            "source_clause": "제18조제1항제4호",
            "link_text": "대통령령",
            "line_text": "대통령령이 정하는",
            "target_law_name": "사행산업통합감독위원회법 시행령",
            "target_article_no": "제12조",
            "target_article_title": "과도한 사행심 유발 영업행위",
            "target_mst": "284761",
            "target_url": "https://www.law.go.kr/법령/사행산업통합감독위원회법 시행령/제12조",
            "resolve_method": "lsDelegated",
            "source_provision_id": "law:사행산업통합감독위원회법#JO0018",
            "reference_id": "law:사행산업통합감독위원회법시행령#JO0012"
          }
        ],
        "images": [],
        "provision_id": "law:사행산업통합감독위원회법#JO0018"
      },
      {
        "article_no": "제18조의2",
        "article_title": "불법사행산업 등의 신고 등",
        "chapter": "",
        "content": "제18조의2(불법사행산업 등의 신고 등)\n① 누구든지 불법사행산업 또는 사행산업사업자의 과도한 사행심 유발행위나 준수사항 위반행위를 알게 된 경우에는 이를 위원회에 신고할 수 있다.\n② 위원회는 제1항에 따른 신고를 접수한 경우에는 고발 및 수사 의뢰 등 필요한 조치를 할 수 있다.\n③ 위원회는 제1항에 따른 신고를 한 자에게 예산의 범위에서 신고포상금을 지급할 수 있다.\n④ 제3항에 따른 포상금의 지급 기준ㆍ방법 및 절차 등에 필요한 사항은 위원회규칙으로 정한다.",
        "enforcement_date": "20260602",
        "relations": [],
        "images": [],
        "provision_id": "law:사행산업통합감독위원회법#JO0018_02"
      },
      {
        "article_no": "제18조의3",
        "article_title": "불법사행산업 감시ㆍ신고센터 등",
        "chapter": "",
        "content": "제18조의3(불법사행산업 감시ㆍ신고센터 등)\n① 불법사행산업의 감시를 위하여 사무처에 불법사행산업 감시ㆍ신고센터를 둔다.\n② 제1항에 따른 불법사행산업 감시ㆍ신고센터의 조직ㆍ업무에 필요한 사항은 대통령령으로 정하고, 운영에 필요한 사항은 위원회규칙으로 정한다.\n③ 위원회는 불법사행산업의 감시를 위하여 필요한 경우 수사기관 또는 사행산업사업자에게 협조를 요청할 수 있다.\n④ 제3항에 따른 협조요청을 받은 사행산업사업자는 특별한 사정이 없는 한 이에 따라야 하며, 그 결과를 위원회에 통보하여야 한다.",
        "enforcement_date": "20260602",
        "relations": [
          {
            "relation_type": "delegation",
            "delegation_type": "시행령",
            "target_category": "법령",
            "source_article_no": "제18조의3",
            "source_clause": "제18조의3제2항",
            "link_text": "대통령령",
            "line_text": "대통령령으로 정하고",
            "target_law_name": "사행산업통합감독위원회 사무처 직제",
            "target_article_no": "제8조",
            "target_article_title": "불법사행산업 감시ㆍ신고센터",
            "target_mst": "281525",
            "target_url": "https://www.law.go.kr/법령/사행산업통합감독위원회 사무처 직제/제8조",
            "resolve_method": "lsDelegated",
            "source_provision_id": "law:사행산업통합감독위원회법#JO0018_03",
            "reference_id": "law:사행산업통합감독위원회사무처직제#JO0008"
          }
        ],
        "images": [],
        "provision_id": "law:사행산업통합감독위원회법#JO0018_03"
      },
      {
        "article_no": "제18조의4",
        "article_title": "청소년 도박예방교육과 학교교육의 연계",
        "chapter": "",
        "content": "제18조의4(청소년 도박예방교육과 학교교육의 연계)\n① 위원회는 청소년 도박예방교육과 「교육기본법」에 따른 학교교육을 연계할 수 있도록 필요한 시책을 수립ㆍ시행하여야 한다. <개정 2025.11.11>\n② 위원회는 제1항에 따른 시책을 수립할 때에는 미리 관계 기관과 협의하여야 하며, 전문가의 의견을 들어야 한다.\n③ 제2항에 따른 협의를 요청받은 관계 기관은 특별한 사유가 없으면 이에 따라야 한다.\n④ 「초ㆍ중등교육법」 제2조에 따른 각급 학교의 장은 제1항에 따른 시책에 따라 연 2회 이상 학생을 대상으로 청소년 도박예방교육을 실시하여야 한다. <신설 2025.11.11>",
        "enforcement_date": "20260602",
        "relations": [
          {
            "relation_type": "citation",
            "delegation_type": null,
            "target_category": "법령",
            "source_article_no": "제18조의4",
            "source_clause": "제18조의4",
            "link_text": "「교육기본법」",
            "line_text": "",
            "target_law_name": "교육기본법",
            "target_article_no": "",
            "target_article_title": "",
            "target_mst": "285783",
            "target_url": "https://www.law.go.kr/법령/교육기본법",
            "resolve_method": "rendered_link",
            "source_provision_id": "law:사행산업통합감독위원회법#JO0018_04",
            "reference_id": "law:교육기본법#DOC"
          },
          {
            "relation_type": "citation",
            "delegation_type": null,
            "target_category": "법령",
            "source_article_no": "제18조의4",
            "source_clause": "제18조의4",
            "link_text": "「초ㆍ중등교육법」",
            "line_text": "",
            "target_law_name": "초ㆍ중등교육법",
            "target_article_no": "",
            "target_article_title": "",
            "target_mst": "279605",
            "target_url": "https://www.law.go.kr/법령/초ㆍ중등교육법",
            "resolve_method": "rendered_link",
            "source_provision_id": "law:사행산업통합감독위원회법#JO0018_04",
            "reference_id": "law:초중등교육법#DOC"
          },
          {
            "relation_type": "citation",
            "delegation_type": null,
            "target_category": "법령",
            "source_article_no": "제18조의4",
            "source_clause": "제18조의4",
            "link_text": "제2조",
            "line_text": "",
            "target_law_name": "초ㆍ중등교육법",
            "target_article_no": "제2조",
            "target_article_title": "학교의 종류",
            "target_mst": "279605",
            "target_url": "https://www.law.go.kr/법령/초ㆍ중등교육법/제2조",
            "resolve_method": "rendered_link",
            "source_provision_id": "law:사행산업통합감독위원회법#JO0018_04",
            "reference_id": "law:초중등교육법#JO0002"
          }
        ],
        "images": [],
        "provision_id": "law:사행산업통합감독위원회법#JO0018_04"
      },
      {
        "article_no": "제19조",
        "article_title": "현장 실태 조사ㆍ연구 등",
        "chapter": "",
        "content": "제19조(현장 실태 조사ㆍ연구 등)\n①위원회는 사행산업의 부작용 예방과 치유 등을 위한 현장 실태 조사와 연구 활동을 수행하여야 하며, 필요한 경우 그 결과를 발표할 수 있다.\n②제1항의 규정에 따른 현장 실태 조사와 연구 활동의 결과 발표 등에 관하여 필요한 사항은 위원회규칙으로 정한다.",
        "enforcement_date": "20260602",
        "relations": [],
        "images": [],
        "provision_id": "law:사행산업통합감독위원회법#JO0019"
      },
      {
        "article_no": "제20조",
        "article_title": "권고",
        "chapter": "",
        "content": "제20조(권고) 위원회는 위원회의 업무 수행을 위하여 필요하다고 인정하는 경우에는 사행산업사업자에 대한 시정 명령 등의 필요한 조치를 소관 행정기관의 장에게 권고할 수 있다.",
        "enforcement_date": "20260602",
        "relations": [],
        "images": [],
        "provision_id": "law:사행산업통합감독위원회법#JO0020"
      },
      {
        "article_no": "제21조",
        "article_title": "자료 요청 등",
        "chapter": "",
        "content": "제21조(자료 요청 등)\n①위원회와 기획예산처ㆍ문화체육관광부ㆍ농림축산식품부 등 관련 행정기관은 업무 수행에 필요하다고 인정되는 경우 상호 간에 자료를 요청할 수 있다. <개정 2008.2.29, 2012.5.23, 2013.3.23, 2025.10.1>\n②위원회는 업무 수행을 위하여 필요하다고 인정되는 경우에는 사행산업사업자에 대하여 필요한 자료를 요청할 수 있다.\n③제1항 또는 제2항의 규정에 따라 자료 요청을 받은 관련 행정기관과 사행산업사업자는 특별한 사유가 없는 한 이에 응하여야 한다.\n④위원회는 업무 수행을 위하여 필요하다고 인정하는 경우 사행산업과 관련한 이해관계인과 전문가를 참석하게 하여 의견을 들을 수 있다.",
        "enforcement_date": "20260602",
        "relations": [],
        "images": [],
        "provision_id": "law:사행산업통합감독위원회법#JO0021"
      },
      {
        "article_no": "제22조",
        "article_title": "경비 등 지원",
        "chapter": "",
        "content": "제22조(경비 등 지원) 위원회의 위원에 대하여는 예산의 범위 안에서 회의 참석 수당 그 밖에 직무 수행 경비 등의 실비를 지급할 수 있다.",
        "enforcement_date": "20260602",
        "relations": [],
        "images": [],
        "provision_id": "law:사행산업통합감독위원회법#JO0022"
      },
      {
        "article_no": "제23조",
        "article_title": "비밀누설의 금지",
        "chapter": "",
        "content": "제23조(비밀누설의 금지) 현재 위원회의 위원, 전문위원 또는 직원이거나 과거에 위원, 전문위원 또는 직원의 직에 있었던 자 및 위원회에 파견되거나 위원회의 위촉에 따라 위원회의 업무를 수행하거나 수행하였던 자는 업무처리 중 알게 된 비밀을 타인에게 누설하거나 직무상 목적 외에 이를 사용하여서는 아니된다.",
        "enforcement_date": "20260602",
        "relations": [],
        "images": [],
        "provision_id": "law:사행산업통합감독위원회법#JO0023"
      },
      {
        "article_no": "제24조",
        "article_title": "벌칙 적용에서의 공무원 의제",
        "chapter": "",
        "content": "제24조(벌칙 적용에서의 공무원 의제) 공무원이 아닌 위원회의 위원, 전문위원 및 직원은 위원회의 업무와 관련하여 「형법」 그 밖의 법률에 따른 벌칙을 적용할 때 공무원으로 본다.",
        "enforcement_date": "20260602",
        "relations": [
          {
            "relation_type": "citation",
            "delegation_type": null,
            "target_category": "법령",
            "source_article_no": "제24조",
            "source_clause": "제24조",
            "link_text": "「형법」",
            "line_text": "",
            "target_law_name": "형법",
            "target_article_no": "",
            "target_article_title": "",
            "target_mst": "284025",
            "target_url": "https://www.law.go.kr/법령/형법",
            "resolve_method": "rendered_link",
            "source_provision_id": "law:사행산업통합감독위원회법#JO0024",
            "reference_id": "law:형법#DOC"
          }
        ],
        "images": [],
        "provision_id": "law:사행산업통합감독위원회법#JO0024"
      },
      {
        "article_no": "제25조",
        "article_title": "벌칙",
        "chapter": "",
        "content": "제25조(벌칙) 제23조의 규정을 위반하여 업무처리 중에 알게 된 비밀을 누설한 자는 2년 이하의 징역 또는 3천만원 이하의 벌금에 처한다.",
        "enforcement_date": "20260602",
        "relations": [
          {
            "relation_type": "internal_ref",
            "delegation_type": null,
            "target_category": "법령",
            "source_article_no": "제25조",
            "source_clause": "제25조",
            "link_text": "제23조",
            "line_text": "",
            "target_law_name": "사행산업통합감독위원회법",
            "target_article_no": "제23조",
            "target_article_title": "비밀누설의 금지",
            "target_mst": "",
            "target_url": "https://www.law.go.kr/법령/사행산업통합감독위원회법/제23조",
            "resolve_method": "rendered_link",
            "source_provision_id": "law:사행산업통합감독위원회법#JO0025",
            "reference_id": "law:사행산업통합감독위원회법#JO0023"
          }
        ],
        "images": [],
        "provision_id": "law:사행산업통합감독위원회법#JO0025"
      }
    ]
  },
  "addenda": [
    {
      "promulgation_date": "20070126",
      "promulgation_no": "08279",
      "addendum_key": "2007012608279",
      "content": "부칙 <제8279호,2007.1.26>\n이 법은 공포 후 6개월이 경과한 날부터 시행한다."
    },
    {
      "promulgation_date": "20080229",
      "promulgation_no": "08852",
      "addendum_key": "2008022908852",
      "content": "부칙(정부조직법) <제8852호,2008.2.29>\n제1조 (시행일) 이 법은 공포한 날부터 시행한다. 다만, ㆍㆍㆍ<생략>ㆍㆍㆍ, 부칙 제6조에 따라 개정되는 법률 중 이 법의 시행 전에 공포되었으나 시행일이 도래하지 아니한 법률을 개정한 부분은 각각 해당 법률의 시행일부터 시행한다.\n제2조부터 제5조까지 생략\n제6조 (다른 법률의 개정) ① 부터 <259> 까지 생략\n<260> 사행산업통합감독위원회법 일부를 다음과 같이 개정한다.\n제6조제2항 각 호 외의 부분 전단을 다음과 같이 한다.\n② 위원회의 위원은 기획재정부차관ㆍ행정안전부차관ㆍ문화체육관광부차관 및 농림수산식품부차관을 당연직으로 하고, 다음 각 호의 어느 하나에 해당하는 자 중에서 문화체육관광부장관ㆍ농림수산식품부장관 및 복권위원회 위원장의 추천을 받은 자를 포함하여 국무총리가 임명하거나 위촉한다.\n제16조제1항, 제17조제1항 및 제21조제1항 중 \"문화관광부ㆍ농림부\"를 각각 \"문화체육관광부ㆍ농림수산식품부\"로 한다.\n<261> 부터 <760> 까지 생략\n제7조 생략"
    },
    {
      "promulgation_date": "20120523",
      "promulgation_no": "11426",
      "addendum_key": "2012052311426",
      "content": "부칙 <제11426호,2012.5.23>\n제1조(시행일) 이 법은 공포 후 6개월이 경과한 날부터 시행한다.\n제2조(설립준비) ① 위원장은 이 법 시행일부터 30일 이내에 7명 이내의 한국도박문제관리센터 설립위원(이하 \"설립위원\"이라 한다)을 위촉하여 센터의 설립에 관한 사무를 처리하게 하여야 한다.\n② 설립위원은 센터의 정관을 작성하여 위원장의 인가를 받아야 한다.\n③ 설립위원은 제2항에 따른 인가를 받은 때에는 지체 없이 연명으로 센터의 설립등기를 하여야 한다.\n④ 설립위원은 센터의 설립등기 후 지체 없이 센터의 이사장에게 사무를 인계하여야 한다.\n⑤ 설립위원은 제4항에 따른 사무인계가 끝난 때에는 해촉된 것으로 본다.\n제3조(당연직 위원에 대한 경과조치) 이 법 시행 당시 위원회의 당연직 위원은 이 법 시행 당시 남은 임기 동안에는 제6조제2항의 개정규정에 따른 당연직 위원으로 본다.\n제4조(다른 법령과의 관계) 이 법 시행 당시 다른 법령에서 종전의 「사행산업통합감독위원회법」 또는 그 규정을 인용한 경우에 이 법 가운데 그에 해당하는 규정이 있으면 종전의 규정을 갈음하여 이 법 또는 이 법의 해당 규정을 인용한 것으로 본다."
    },
    {
      "promulgation_date": "20121211",
      "promulgation_no": "11530",
      "addendum_key": "2012121111530",
      "content": "부칙(국가공무원법) <제11530호,2012.12.11>\n제1조(시행일) 이 법은 공포 후 1년이 경과한 날부터 시행한다. <단서 생략>\n제2조부터 제5조까지 생략\n제6조(다른 법률의 개정) ①부터 <19>까지 생략\n<20> 사행산업통합감독위원회법 일부를 다음과 같이 개정한다.\n제15조제3항 중 \"계약직공무원\"을 \"「국가공무원법」 제26조의5에 따른 임기제공무원\"으로 한다.\n<21>부터 <27>까지 생략\n제7조 생략"
    },
    {
      "promulgation_date": "20130323",
      "promulgation_no": "11690",
      "addendum_key": "2013032311690",
      "content": "부칙(정부조직법) <제11690호,2013.3.23>\n제1조(시행일) ① 이 법은 공포한 날부터 시행한다.\n② 생략\n제2조부터 제5조까지 생략\n제6조(다른 법률의 개정) ①부터 <258>까지 생략\n<259> 사행산업통합감독위원회법 일부를 다음과 같이 개정한다.\n제6조제2항 각 호 외의 부분 전단 중 \"행정안전부ㆍ문화체육관광부ㆍ농림수산식품부\"를 \"안전행정부ㆍ문화체육관광부\"로, \"차관(행정안전부의 차관은 지방세제에 관한 사무를 소관하는 차관으로 하고, 문화체육관광부의 차관은 관광 또는 체육에 관한 사무를 소관하는 차관 중 문화체육관광부장관이 지명하는 차관으로 한다)을\"를 \"차관(안전행정부의 차관은 지방세제에 관한 사무를 소관하는 차관으로 하고, 문화체육관광부의 차관은 관광 또는 체육에 관한 사무를 소관하는 차관 중 문화체육관광부장관이 지명하는 차관으로 한다)과 농림축산식품부차관을\"로, \"농림수산식품부장관\"을 \"농림축산식품부장관\"으로 한다.\n제16조제2항, 제17조제1항 및 제21조제1항 중 \"농림수산식품부\"를 각각 \"농림축산식품부\"로 한다.\n<260>부터 <710>까지 생략\n제7조 생략"
    },
    {
      "promulgation_date": "20141119",
      "promulgation_no": "12844",
      "addendum_key": "2014111912844",
      "content": "부칙(정부조직법) <제12844호,2014.11.19>\n제1조(시행일) 이 법은 공포한 날부터 시행한다. 다만, 부칙 제6조에 따라 개정되는 법률 중 이 법 시행 전에 공포되었으나 시행일이 도래하지 아니한 법률을 개정한 부분은 각각 해당 법률의 시행일부터 시행한다.\n제2조부터 제5조까지 생략\n제6조(다른 법률의 개정) ①부터 <169>까지 생략\n<170> 사행산업통합감독위원회법 일부를 다음과 같이 개정한다.\n제6조제2항 각 호 외의 부분 전단 중 \"기획재정부ㆍ안전행정부ㆍ문화체육관광부의 사행산업에 관한 사무를 소관하는 각 차관(안전행정부의 차관은 지방세제에 관한 사무를 소관하는 차관으로 하고, 문화체육관광부의 차관은 관광 또는 체육에 관한 사무를 소관하는 차관 중 문화체육관광부장관이 지명하는 차관으로 한다)\"을 \"기획재정부의 사행사업에 관한 사무를 소관하는 차관, 행정자치부차관, 문화체육관광부의 사행산업에 관한 사무를 소관하는 차관\"으로 한다.\n<171>부터 <258>까지 생략\n제7조 생략"
    },
    {
      "promulgation_date": "20170726",
      "promulgation_no": "14839",
      "addendum_key": "2017072614839",
      "content": "부칙(정부조직법) <제14839호,2017.7.26>\n제1조(시행일) ① 이 법은 공포한 날부터 시행한다. 다만, 부칙 제5조에 따라 개정되는 법률 중 이 법 시행 전에 공포되었으나 시행일이 도래하지 아니한 법률을 개정한 부분은 각각 해당 법률의 시행일부터 시행한다.\n제2조부터 제4조까지 생략\n제5조(다른 법률의 개정) ①부터 <129>까지 생략\n<130> 사행산업통합감독위원회법 일부를 다음과 같이 개정한다.\n제6조제2항 각 호 외의 부분 전단 중 \"행정자치부차관\"을 \"행정안전부차관\"으로 한다.\n<131>부터 <382>까지 생략\n제6조 생략"
    },
    {
      "promulgation_date": "20171219",
      "promulgation_no": "15263",
      "addendum_key": "2017121915263",
      "content": "부칙 <제15263호,2017.12.19>\n제1조(시행일) 이 법은 2018년 1월 1일부터 시행한다.\n제2조(중독예방치유부담금에 관한 경과조치) 이 법 시행 전에 종전의 제14조의2에 따라 부과ㆍ징수된 중독예방치유부담금은 이 법 시행일에 위원장이 사행산업중독예방치유계정에 이체하여야 한다."
    },
    {
      "promulgation_date": "20181016",
      "promulgation_no": "15818",
      "addendum_key": "2018101615818",
      "content": "부칙 <제15818호,2018.10.16>\n제1조(시행일) 이 법은 공포 후 6개월이 경과한 날부터 시행한다.\n제2조(부담금의 분할납부에 관한 적용례) 제14조의2제3항의 개정규정은 이 법 시행 후 최초로 제14조의2제1항에 따라 부담금을 부과하는 경우부터 적용한다.\n제3조(가산금에 관한 경과조치) 이 법 시행 전에 부담금의 납부 독촉을 받은 납부의무자의 가산금에 대하여는 제14조의2제5항의 개정규정에도 불구하고 종전의 규정에 따른다."
    },
    {
      "promulgation_date": "20181224",
      "promulgation_no": "16059",
      "addendum_key": "2018122416059",
      "content": "부칙 <제16059호,2018.12.24>\n제1조(시행일) 이 법은 공포한 날부터 시행한다.\n제2조(센터 임원에 대한 경과조치) 제14조제3항의 개정규정 시행 당시 종전의 규정에 따라 선임된 임원은 같은 개정규정에 따라 임명된 것으로 본다."
    },
    {
      "promulgation_date": "20191126",
      "promulgation_no": "16598",
      "addendum_key": "2019112616598",
      "content": "부칙 <제16598호,2019.11.26>\n제1조(시행일) 이 법은 공포 후 3개월이 경과한 날부터 시행한다.\n제2조(종합계획에 관한 적용례) 제16조제1항제7호의 개정규정은 이 법 시행 후 종합계획을 수립하는 경우부터 적용한다."
    },
    {
      "promulgation_date": "20220118",
      "promulgation_no": "18773",
      "addendum_key": "2022011818773",
      "content": "부칙 <제18773호,2022.1.18>\n제1조(시행일) 이 법은 공포 후 6개월이 경과한 날부터 시행한다.\n제2조(한국도박문제관리센터의 명칭변경에 따른 경과조치) 이 법 시행 당시 종전의 규정에 따라 설립된 한국도박문제관리센터는 이 법의 개정규정에 따라 설립된 한국도박문제예방치유원으로 본다."
    },
    {
      "promulgation_date": "20230620",
      "promulgation_no": "19482",
      "addendum_key": "2023062019482",
      "content": "부칙 <제19482호,2023.6.20>\n제1조(시행일) 이 법은 공포 후 6개월이 경과한 날부터 시행한다.\n제2조(위원회의 구성에 관한 적용례) 제6조제2항제2호의 개정규정은 이 법 시행 이후 위원회의 위원을 위촉하는 경우부터 적용한다.\n제3조(중독예방치유부담금의 부과ㆍ징수 비율에 관한 적용례) 제14조의2제1항 본문 및 같은 조 제2항의 개정규정은 이 법 시행 이후 위원회가 부과ㆍ징수하는 중독예방치유부담금부터 적용한다."
    },
    {
      "promulgation_date": "20251001",
      "promulgation_no": "21065",
      "addendum_key": "2025100121065",
      "content": "부칙(정부조직법) <제21065호,2025.10.1>\n제1조(시행일) 이 법은 공포한 날부터 시행한다. 다만, 부칙 제7조에 따라 개정되는 법률 중 이 법 시행 전에 공포되었으나 시행일이 도래하지 아니한 법률을 개정한 부분은 각각 해당 법률의 시행일부터 시행하고, 다음 각 호의 개정규정은 해당 호에서 정하는 날부터 시행한다.\n1. 다음 각 목의 개정규정은 2026년 1월 2일부터 시행한다. 다만, 부칙 제7조에 따라 개정되는 법률(가목 및 나목의 개정규정과 관련되는 부분으로 한정한다) 중 본문에 따른 시행일 전에 공포되었으나 본문에 따른 시행일이 도래하지 아니한 법률을 개정한 부분은 각각 해당 법률의 시행일부터 시행한다.\n가. 제19조제4항, 제23조, 제29조제1항제1호 및 제30조의 개정규정\n나. 제12조제2항, 제19조제3항, 제22조 및 제29조제2항 단서의 개정규정(재정경제부장관 및 재정경제부에 관한 부분으로 한정한다)\n다. 부칙 제7조에 따라 개정되는 법률(가목 및 나목의 개정규정과 관련되는 부분으로 한정한다)\n2. 생략\n제2조부터 제6조까지 생략\n제7조(다른 법률의 개정) ①부터 <171>까지 생략\n<172> 사행산업통합감독위원회법 일부를 다음과 같이 개정한다.\n제6조제2항 각 호 외의 부분 전단 중 \"기획재정부의 사행사업에 관한 사무를 소관하는 차관\"을 \"기획예산처차관\"으로 한다.\n제16조제2항, 제17조제1항 및 제21조제1항 중 \"기획재정부\"를 각각 \"기획예산처\"로 한다.\n<173>부터 <626>까지 생략\n제8조 생략"
    },
    {
      "promulgation_date": "20251111",
      "promulgation_no": "21092",
      "addendum_key": "2025111121092",
      "content": "부칙 <제21092호,2025.11.11>\n이 법은 공포 후 6개월이 경과한 날부터 시행한다."
    },
    {
      "promulgation_date": "20251230",
      "promulgation_no": "21254",
      "addendum_key": "2025123021254",
      "content": "부칙(석탄산업전환지역 개발 지원에 관한 특별법) <제21254호,2025.12.30>\n제1조(시행일) 이 법은 공포 후 3개월이 경과한 날부터 시행한다. <단서 생략>\n제2조(다른 법률의 개정) ① 및 ② 생략\n③ 사행산업통합감독위원회법 일부를 다음과 같이 개정한다.\n제2조제1호가목 중 \"「폐광지역개발 지원에 관한 특별법」\"을 \"「석탄산업전환지역 개발 지원에 관한 특별법」\"으로 하고, 같은 조 제2호가목 중 \"「폐광지역개발 지원에 관한 특별법」\"을 \"「석탄산업전환지역 개발 지원에 관한 특별법」\"으로 한다.\n제14조의2제1항 단서 중 \"「폐광지역 개발 지원에 관한 특별법」\"을 \"「석탄산업전환지역 개발 지원에 관한 특별법」\"으로 한다.\n④부터 ⑨까지 생략"
    },
    {
      "promulgation_date": "20260602",
      "promulgation_no": "21748",
      "addendum_key": "2026060221748",
      "content": "부칙 <제21748호,2026.6.2>\n제1조(시행일) 이 법은 공포한 날부터 시행한다.\n제2조(이의신청에 관한 적용례) 제14조의2의 개정규정은 이 법 시행 이후 부과ㆍ징수하는 부담금부터 적용한다."
    }
  ],
  "appendices": [],
  "ordinance_delegations": [],
  "relation_stats": {
    "relations_total": 71,
    "by_category": {
      "법령": 67,
      "행정규칙": 2,
      "학칙공단": 2
    },
    "by_relation_type": {
      "citation": 41,
      "delegation": 17,
      "internal_ref": 13
    },
    "articles_total": 31,
    "articles_with_relations": 18,
    "unmatched_relations": 0,
    "ordinance_groups": 0,
    "ordinance_docs_total": 0,
    "addenda_count": 17,
    "appendices_count": 0
  },
  "source": {
    "source_url": "https://www.law.go.kr/법령/사행산업통합감독위원회법"
  },
  "provision_id": "law:사행산업통합감독위원회법#DOC",
  "future_enforcement_dates": [],
  "version_count": 1
}