{
  "law_id": "014094",
  "mst": "278499",
  "version_uid": "014094:278499:20251001",
  "law_name": "공공폐자원관리시설의 설치ㆍ운영 및 주민지원 등에 관한 특별법 시행령",
  "law_abbr": "공공폐자원관리시설법 시행령",
  "law_type": "대통령령",
  "promulgation_no": "35804",
  "promulgation_date": "20251001",
  "enforcement_date": "20251001",
  "revision_date": "20251001",
  "revision_type": "타법개정",
  "is_current": true,
  "is_future": false,
  "basic_info": {
    "법령명_한글": "공공폐자원관리시설의 설치ㆍ운영 및 주민지원 등에 관한 특별법 시행령",
    "별표시행일자문자열": "20251001:별표1,별표3",
    "공포번호": "35804",
    "전화번호": "044-201-7367, 7378",
    "법령명_영어": "ENFORCEMENT DECREE ON THE SPECIAL ACT ON THE INSTALLATION AND OPERATION OF PUBLIC WASTE RESOURCES MANAGEMENT FACILITIES AND RESIDENT SUPPORT",
    "언어": "한글",
    "제개정구분": "타법개정",
    "법령ID": "014094",
    "공동부령정보": "",
    "소관부처": {
      "content": "기후에너지환경부",
      "소관부처코드": "1482000"
    },
    "공포법령여부": "N",
    "법종구분": {
      "content": "대통령령",
      "법종구분코드": "A0007"
    },
    "시행일자": "20251001",
    "별표편집여부": "편집",
    "연락부서": {
      "부서단위": {
        "부서연락처": "044-201-7367, 7378",
        "부서키": "393067",
        "부서명": "폐자원관리과",
        "소관부처명": "기후에너지환경부",
        "소관부처코드": "1482000"
      }
    },
    "법령명_한자": "공공폐자원관리시설의 설치ㆍ운영 및 주민지원 등에 관한 특별법 시행령",
    "법령명약칭": "공공폐자원관리시설법 시행령",
    "공포일자": "20251001",
    "편장절관": "39030000"
  },
  "amendment_text": "⊙대통령령 제35804호(2025.10.1)\n기후에너지환경부와 그 소속기관 직제\n[본문 생략]\n부칙\n제1조(시행일) 이 영은 공포한 날부터 시행한다. 다만, 부칙 제6조에 따라 개정되는 대통령령 중 이 영 시행 전에 공포되었으나 시행일이 도래하지 아니한 대통령령을 개정한 부분은 각각 해당 대통령령의 시행일부터 시행한다.\n제2조부터 제4조까지 생략\n제5조(다른 법령의 개정) ①부터 ③까지 생략\n④ 공공폐자원관리시설의 설치ㆍ운영 및 주민지원 등에 관한 특별법 시행령 일부를 다음과 같이 개정한다.\n제2조제1항제4호, 같은 조 제2항, 제5조제1항, 제6조제2항제1호ㆍ제2호, 제8조제1항 각 호 외의 부분, 제12조제2항, 제13조제6항제3호, 제15조제4항, 제16조제1항제3호, 같은 조 제2항제2호, 제20조제3항, 제22조제2항 각 호 외의 부분, 같은 조 제3항, 제23조제2항 및 제24조 각 호 외의 부분 중 \"환경부장관\"을 각각 \"기후에너지환경부장관\"으로 한다.\n제5조제1항 및 제6조제2항제1호 중 \"환경부의\"를 각각 \"기후에너지환경부의\"로 한다.\n제10조제1항 각 호 외의 부분, 제13조제7항 각 호 외의 부분 및 제22조제2항 각 호 외의 부분 중 \"환경부령\"을 각각 \"기후에너지환경부령\"으로 한다.\n별표 1 제1호가목5)ㆍ7), 같은 호 나목5)ㆍ7), 별표 3 제1호2) 및 같은 표 제4호 중 \"환경부장관\"을 각각 \"기후에너지환경부장관\"으로 한다.\n별표 1 제1호가목6) 및 같은 호 나목6) 중 \"환경부\"를 각각 \"기후에너지환경부\"로 한다.\n⑤부터 <80>까지 생략",
  "revision_reason": "[제정]\n◇ 제정이유\n환경, 기후변화 대응 및 에너지(원자력발전의 수출 및 석유ㆍ석탄ㆍ가스ㆍ광물 등 자원 관련 사무 제외)에 관한 사무를 관장하기 위하여 환경부를 기후에너지환경부로 개편하는 등의 내용으로 「정부조직법」이 개정(법률 제21065호, 2025. 10. 1. 공포ㆍ시행)됨에 따라, 기후에너지환경부와 그 소속기관의 조직과 직무범위 및 정원 등을 구체적으로 정하려는 것임.\n◇ 주요내용\n가. 기후에너지환경부의 직무(제3조)\n기후에너지환경부는 기후변화 대응, 자연환경ㆍ생활환경의 보전, 환경오염방지, 수자원의 보전ㆍ이용ㆍ개발, 하천 및 에너지에 관한 사무를 관장하도록 함.\n나. 기후에너지환경부에 두는 하부조직(제4조 및 제6조부터 제17조까지)\n기후에너지환경부에 하부조직으로 대변인ㆍ감사관ㆍ장관정책보좌관ㆍ기획조정실장ㆍ운영지원과ㆍ물관리정책실ㆍ자연보전국ㆍ대기환경국ㆍ자원순환국ㆍ환경보건국ㆍ기후에너지정책실 및 에너지전환정책실을 둠.\n다. 기후에너지환경부의 소속기관(제19조부터 제68조까지)\n기후에너지환경부장관의 소속기관으로 국립환경과학원ㆍ국립환경인재개발원ㆍ온실가스 종합정보센터ㆍ국가미세먼지정보센터ㆍ국립야생동물질병관리원ㆍ유역환경청ㆍ지방환경청ㆍ수도권대기환경청ㆍ홍수통제소ㆍ중앙환경분쟁조정피해구제위원회사무국ㆍ전기위원회ㆍ국립생물자원관 및 화학물질안전원을 둠.\n라. 기후에너지환경부와 그 소속기관에 두는 공무원의 정원(제69조ㆍ제70조, 별표 4 및 별표 5)\n기후에너지환경부에 822명(정무직 3명, 별정직 5명, 고위공무원단 22명, 3급 또는 4급 이하 789명, 전문경력관 3명)의 정원을 두고, 기후에너지환경부 소속기관에 1,832명(고위공무원단 17명, 3급 또는 4급 이하 1,814명, 전문경력관 1명)의 정원을 둠.\n마. 기후에너지환경부에 두는 평가대상 조직(제73조 및 별표 6)\n기후에너지환경부에 물관리정책실 1개 과, 기후에너지정책실 2개 정책관등, 기후에너지정책실 1개 과, 에너지전환정책실 2개 정책관등 및 에너지전환정책실 3개 과를 평가대상 조직으로 둠.\n바. 기후에너지환경부에 두는 한시정원(제74조 및 별표 7)\n기후에너지환경부에 통합환경관리제도 운영 등의 업무를 추진하기 위하여 2025년 12월 31일까지 존속하는 인력 2명(5급 이하 2명), 수자원개발 업무를 추진하기 위하여 2025년 12월 31일까지 존속하는 인력 2명(5급 이하 2명), 가습기살균제 피해자 지원 등의 업무를 추진하기 위하여 2026년 12월 31일까지 존속하는 인력 2명(5급 이하 2명), 순환경제 신기술ㆍ서비스에 대한 규제 특례 업무를 추진하기 위하여 2026년 12월 31일까지 존속하는 인력 1명(5급 이하 1명) 및 새만금환경생태용지 조성 및 운영 업무를 추진하기 위하여 2027년 12월 31일까지 존속하는 인력 3명(6급 이하 3명)을 각각 한시정원으로 둠.\n<법제처 제공>",
  "body": {
    "format": "articles",
    "article_count": 24,
    "articles": [
      {
        "article_no": "제1조",
        "article_title": "목적",
        "chapter": "제1장 총칙",
        "content": "제1조(목적) 이 영은 「공공폐자원관리시설의 설치ㆍ운영 및 주민지원 등에 관한 특별법」에서 위임된 사항과 그 시행에 필요한 사항을 규정함을 목적으로 한다.",
        "enforcement_date": "20251001",
        "relations": [
          {
            "relation_type": "citation",
            "delegation_type": null,
            "target_category": "법령",
            "source_article_no": "제1조",
            "source_clause": "제1조",
            "link_text": "「공공폐자원관리시설의 설치ㆍ운영 및 주민지원 등에 관한 특별법」",
            "line_text": "제1조(목적) 이 영은 「공공폐자원관리시설의 설치ㆍ운영 및 주민지원 등에 관한 특별법」에서 위임된 사항과 그 시행에 필요한 사항을 규정함을 목적으로 한다.",
            "target_law_name": "공공폐자원관리시설의 설치ㆍ운영 및 주민지원 등에 관한 특별법",
            "target_article_no": "",
            "target_article_title": "",
            "target_mst": "",
            "target_url": "https://www.law.go.kr/법령/공공폐자원관리시설의 설치ㆍ운영 및 주민지원 등에 관한 특별법",
            "resolve_method": "text_parse",
            "source_provision_id": "law:공공폐자원관리시설의설치운영및주민지원등에관한특별법시행령#JO0001",
            "reference_id": "law:공공폐자원관리시설의설치운영및주민지원등에관한특별법#DOC"
          }
        ],
        "images": [],
        "provision_id": "law:공공폐자원관리시설의설치운영및주민지원등에관한특별법시행령#JO0001"
      },
      {
        "article_no": "제2조",
        "article_title": "공공처리대상폐기물",
        "chapter": "제1장 총칙",
        "content": "제2조(공공처리대상폐기물)\n① 「공공폐자원관리시설의 설치ㆍ운영 및 주민지원 등에 관한 특별법」(이하 \"법\"이라 한다) 제2조제7호라목에서 \"대통령령으로 정하는 폐기물\"이란 다음 각 호의 폐기물을 말한다. <개정 2025.10.1>\n1.  「폐기물관리법」 제25조의4에 따른 의료폐기물\n2.  「폐기물관리법 시행령」 별표 1 제10호의2에 따른 천연방사성제품폐기물\n3.  「폐기물관리법 시행령」 별표 1 제11호에 따른 수은폐기물\n4.  그 밖에 폐기물처리시설의 부족 등으로 폐기물의 원활한 처리가 어려워 국민건강과 재산에 대한 피해가 발생할 우려가 있다고 기후에너지환경부장관이 인정하여 고시하는 폐기물\n② 기후에너지환경부장관은 제1항제4호에 따라 공공처리대상폐기물을 고시하려는 경우에는 전문가 및 이해관계자의 의견을 수렴하고, 법 제7조제1항에 따른 설치ㆍ운영기관(이하 \"관리시설설치ㆍ운영기관\"이라 한다) 및 지방자치단체 등 관계기관과 협의해야 한다. <개정 2025.10.1>",
        "enforcement_date": "20251001",
        "relations": [
          {
            "relation_type": "citation",
            "delegation_type": null,
            "target_category": "법령",
            "source_article_no": "제2조",
            "source_clause": "제2조제1항제2호",
            "link_text": "「폐기물관리법 시행령」",
            "line_text": "2.  「폐기물관리법 시행령」 별표 1 제10호의2에 따른 천연방사성제품폐기물",
            "target_law_name": "폐기물관리법 시행령",
            "target_article_no": "",
            "target_article_title": "",
            "target_mst": "",
            "target_url": "https://www.law.go.kr/법령/폐기물관리법 시행령",
            "resolve_method": "text_parse",
            "source_provision_id": "law:공공폐자원관리시설의설치운영및주민지원등에관한특별법시행령#JO0002",
            "reference_id": "law:폐기물관리법시행령#DOC"
          },
          {
            "relation_type": "appendix_ref",
            "delegation_type": null,
            "target_category": "별표",
            "source_article_no": "제2조",
            "source_clause": "제2조제1항제2호",
            "link_text": "별표 1",
            "line_text": "2.  「폐기물관리법 시행령」 별표 1 제10호의2에 따른 천연방사성제품폐기물",
            "target_law_name": "폐기물관리법 시행령",
            "target_article_no": "별표1",
            "target_article_title": "",
            "appendix_no": "1",
            "appendix_branch": "",
            "appendix_kind": "별표",
            "appendix_found": false,
            "appendix_dangling": false,
            "target_mst": "",
            "target_url": "https://www.law.go.kr/법령/폐기물관리법 시행령",
            "resolve_method": "text_parse_external",
            "source_provision_id": "law:공공폐자원관리시설의설치운영및주민지원등에관한특별법시행령#JO0002",
            "reference_id": "law:폐기물관리법시행령#BYL0001"
          }
        ],
        "images": [],
        "provision_id": "law:공공폐자원관리시설의설치운영및주민지원등에관한특별법시행령#JO0002"
      },
      {
        "article_no": "제3조",
        "article_title": "공공폐자원관리시설 기본계획",
        "chapter": "제2장 공공폐자원관리시설의 설치ㆍ운영 등",
        "content": "제3조(공공폐자원관리시설 기본계획) 법 제5조제2항제4호에서 \"대통령령으로 정하는 사항\"이란 공공폐자원관리시설의 입지 주변에 거주하는 주민의 지원에 관한 사항을 말한다.",
        "enforcement_date": "20251001",
        "relations": [],
        "images": [],
        "provision_id": "law:공공폐자원관리시설의설치운영및주민지원등에관한특별법시행령#JO0003"
      },
      {
        "article_no": "제4조",
        "article_title": "공공폐자원관리시설의 설치ㆍ운영 등",
        "chapter": "제2장 공공폐자원관리시설의 설치ㆍ운영 등",
        "content": "제4조(공공폐자원관리시설의 설치ㆍ운영 등) 법 제6조제1항제3호에서 \"대통령령으로 정하는 자\"란 다음 각 호의 자를 말한다.\n1.  「수도권매립지관리공사의 설립 및 운영 등에 관한 법률」에 따라 설립된 수도권매립지관리공사\n2.  법 제6조제4항에 따른 지정기준을 갖춘 기관이나 단체",
        "enforcement_date": "20251001",
        "relations": [
          {
            "relation_type": "citation",
            "delegation_type": null,
            "target_category": "법령",
            "source_article_no": "제4조",
            "source_clause": "제4조제1호",
            "link_text": "「수도권매립지관리공사의 설립 및 운영 등에 관한 법률」",
            "line_text": "1.  「수도권매립지관리공사의 설립 및 운영 등에 관한 법률」에 따라 설립된 수도권매립지관리공사",
            "target_law_name": "수도권매립지관리공사의 설립 및 운영 등에 관한 법률",
            "target_article_no": "",
            "target_article_title": "",
            "target_mst": "",
            "target_url": "https://www.law.go.kr/법령/수도권매립지관리공사의 설립 및 운영 등에 관한 법률",
            "resolve_method": "text_parse",
            "source_provision_id": "law:공공폐자원관리시설의설치운영및주민지원등에관한특별법시행령#JO0004",
            "reference_id": "law:수도권매립지관리공사의설립및운영등에관한법률#DOC"
          }
        ],
        "images": [],
        "provision_id": "law:공공폐자원관리시설의설치운영및주민지원등에관한특별법시행령#JO0004"
      },
      {
        "article_no": "제5조",
        "article_title": "공공폐자원관리시설 입지후보지 선정계획의 수립ㆍ공고 등",
        "chapter": "제2장 공공폐자원관리시설의 설치ㆍ운영 등",
        "content": "제5조(공공폐자원관리시설 입지후보지 선정계획의 수립ㆍ공고 등)\n① 기후에너지환경부장관은 법 제7조제3항에 따라 같은 조 제1항에 따른 입지후보지 선정계획(이하 \"입지후보지선정계획\"이라 한다)을 관보와 기후에너지환경부의 인터넷 홈페이지에 공고해야 한다. <개정 2025.10.1>\n② 법 제7조제4항에서 \"대통령령으로 정하는 중요한 사항\"이란 다음 각 호의 사항을 말한다.\n1.  처리대상 폐기물의 종류 및 공공폐자원관리시설의 종류\n2.  처리대상 폐기물의 처리량(100분의 30 이상 증가하는 경우로 한정한다)\n3.  공공폐자원관리시설의 규모(100분의 30 이상 증가하는 경우로 한정한다)\n4.  공공폐자원관리시설의 입지후보지 선정방법\n③ 관리시설설치ㆍ운영기관은 입지후보지선정계획에 따라 공공폐자원관리시설의 입지후보지를 공모하려는 경우에는 법 제7조제1항 각 호 및 다음 각 호의 사항을 관리시설설치ㆍ운영기관의 홈페이지에 공고해야 한다.\n1.  공모기간\n2.  부지면적 등 설치희망부지의 요건\n3.  그 밖에 응모방법 등 입지후보지 응모에 필요한 사항\n④ 공공폐자원관리시설의 설치희망부지는 법 제7조제5항에 해당하는 지역으로서 다음 각 호의 요건을 모두 갖추어야 한다.\n1.  공공폐자원관리시설의 설치에 필요한 최소한의 부지면적을 갖출 것\n2.  단층 지형 등 공공폐자원관리시설의 설치에 부적합한 지형에 해당하지 않을 것\n⑤ 법 제7조제5항에 따른 공모절차에 필요한 구비서류는 다음 각 호와 같다.\n1.  제4항에 따른 설치희망부지의 요건을 모두 갖추었음을 증명하는 서류\n2.  주민동의서(법 제7조제5항제3호에 따른 지역에 해당하는 경우로 한정한다)\n⑥ 법 제7조제5항에 따른 입지후보지의 선정공모에 참여하려는 자는 제1항에 따른 공고내용에 따라 관리시설설치ㆍ운영기관에 입지후보지 선정을 신청해야 한다.\n⑦ 관리시설설치ㆍ운영기관은 제6항에 따라 입지후보지 선정을 신청한 지역 중에서 입지후보지를 선정하면 입지후보지를 관할하는 지방자치단체의 장과 그 의회에 선정 결과를 지체 없이 통보해야 한다.",
        "enforcement_date": "20251001",
        "relations": [],
        "images": [],
        "provision_id": "law:공공폐자원관리시설의설치운영및주민지원등에관한특별법시행령#JO0005"
      },
      {
        "article_no": "제6조",
        "article_title": "공공폐자원관리시설 입지후보지 선정공고",
        "chapter": "제2장 공공폐자원관리시설의 설치ㆍ운영 등",
        "content": "제6조(공공폐자원관리시설 입지후보지 선정공고)\n① 관리시설설치ㆍ운영기관은 입지후보지가 선정된 경우 법 제8조에 따라 다음 각 호의 사항을 포함하여 그 결과를 공고해야 한다.\n1.  처리대상 폐기물의 종류 및 처리량\n2.  공공폐자원관리시설의 종류 및 규모\n3.  선정된 입지후보지의 위치(지번을 포함한다), 지목 및 면적\n② 관리시설설치ㆍ운영기관은 다음 각 호의 구분에 따른 방법으로 제1항 각 호의 사항을 공고해야 한다. <개정 2025.10.1>\n1.  기후에너지환경부장관이 관리시설설치ㆍ운영기관인 경우: 관보 및 기후에너지환경부의 인터넷 홈페이지에 게재\n2.  기후에너지환경부장관 외의 관리시설설치ㆍ운영기관인 경우: 해당 기관의 인터넷 홈페이지 및 입지후보지를 관할하는 특별자치시ㆍ특별자치도ㆍ시ㆍ군 ㆍ구(구는 자치구를 말하며, 이하 \"시ㆍ군ㆍ구\"라 한다)를 주된 보급지역으로 하는 하나 이상의 일간신문에 게재",
        "enforcement_date": "20251001",
        "relations": [],
        "images": [],
        "provision_id": "law:공공폐자원관리시설의설치운영및주민지원등에관한특별법시행령#JO0006"
      },
      {
        "article_no": "제7조",
        "article_title": "공공폐자원관리시설 입지선정",
        "chapter": "제2장 공공폐자원관리시설의 설치ㆍ운영 등",
        "content": "제7조(공공폐자원관리시설 입지선정)\n① 법 제9조제1항에 따른 입지선정위원회(이하 \"입지선정위원회\"라 한다)의 구성 방법은 별표 1과 같다.\n② 법 제9조제2항 본문에서 \"대통령령으로 정하는 전문연구기관\"이란 다음 각 호의 기관을 말한다.\n1.  국공립연구기관\n2.  「정부출연연구기관 등의 설립ㆍ운영 및 육성에 관한 법률」에 따라 설립된 정부출연연구기관\n3.  지방자치단체가 출연한 연구기관\n4.  「특정연구기관 육성법」의 적용을 받는 연구기관\n5.  「고등교육법」 제2조에 따른 학교의 환경 관련 연구소\n6.  「환경영향평가법」 제54조제1항에 따라 등록한 환경영향평가업자\n7.  「엔지니어링산업 진흥법」 제21조에 따라 신고한 엔지니어링사업자",
        "enforcement_date": "20251001",
        "relations": [
          {
            "relation_type": "appendix_ref",
            "delegation_type": null,
            "target_category": "별표",
            "source_article_no": "제7조",
            "source_clause": "제7조제1항",
            "link_text": "별표 1",
            "line_text": "① 법 제9조제1항에 따른 입지선정위원회(이하 \"입지선정위원회\"라 한다)의 구성 방법은 별표 1과 같다.",
            "target_law_name": "공공폐자원관리시설의 설치ㆍ운영 및 주민지원 등에 관한 특별법 시행령",
            "target_article_no": "별표1",
            "target_article_title": "입지선정위원회의 구성 방법(제7조제1항 관련)",
            "appendix_no": "1",
            "appendix_branch": "",
            "appendix_kind": "별표",
            "appendix_found": true,
            "target_mst": "",
            "appendix_dangling": false,
            "target_url": "https://www.law.go.kr/LSW/lsBylInfoPLinkR.do?lsiSeq=278499&bylNo=0001&bylBrNo=00",
            "resolve_method": "text_parse",
            "source_provision_id": "law:공공폐자원관리시설의설치운영및주민지원등에관한특별법시행령#JO0007",
            "reference_id": "law:공공폐자원관리시설의설치운영및주민지원등에관한특별법시행령#BYL0001"
          },
          {
            "relation_type": "citation",
            "delegation_type": null,
            "target_category": "법령",
            "source_article_no": "제7조",
            "source_clause": "제7조제2항제2호",
            "link_text": "「정부출연연구기관 등의 설립ㆍ운영 및 육성에 관한 법률」",
            "line_text": "2.  「정부출연연구기관 등의 설립ㆍ운영 및 육성에 관한 법률」에 따라 설립된 정부출연연구기관",
            "target_law_name": "정부출연연구기관 등의 설립ㆍ운영 및 육성에 관한 법률",
            "target_article_no": "",
            "target_article_title": "",
            "target_mst": "",
            "target_url": "https://www.law.go.kr/법령/정부출연연구기관 등의 설립ㆍ운영 및 육성에 관한 법률",
            "resolve_method": "text_parse",
            "source_provision_id": "law:공공폐자원관리시설의설치운영및주민지원등에관한특별법시행령#JO0007",
            "reference_id": "law:정부출연연구기관등의설립운영및육성에관한법률#DOC"
          },
          {
            "relation_type": "citation",
            "delegation_type": null,
            "target_category": "법령",
            "source_article_no": "제7조",
            "source_clause": "제7조제2항제4호",
            "link_text": "「특정연구기관 육성법」",
            "line_text": "4.  「특정연구기관 육성법」의 적용을 받는 연구기관",
            "target_law_name": "특정연구기관 육성법",
            "target_article_no": "",
            "target_article_title": "",
            "target_mst": "",
            "target_url": "https://www.law.go.kr/법령/특정연구기관 육성법",
            "resolve_method": "text_parse",
            "source_provision_id": "law:공공폐자원관리시설의설치운영및주민지원등에관한특별법시행령#JO0007",
            "reference_id": "law:특정연구기관육성법#DOC"
          }
        ],
        "images": [],
        "provision_id": "law:공공폐자원관리시설의설치운영및주민지원등에관한특별법시행령#JO0007"
      },
      {
        "article_no": "제8조",
        "article_title": "공공폐자원관리시설의 입지 결정ㆍ고시",
        "chapter": "제2장 공공폐자원관리시설의 설치ㆍ운영 등",
        "content": "제8조(공공폐자원관리시설의 입지 결정ㆍ고시)\n① 기후에너지환경부장관은 법 제10조제1항 전단에 따라 다음 각 호의 사항을 포함하여 공공폐자원관리시설의 입지 선정을 결정ㆍ고시해야 한다. <개정 2025.10.1>\n1.  관리시설설치ㆍ운영기관\n2.  처리대상 폐기물의 종류 및 처리량\n3.  공공폐자원관리시설의 종류 및 규모\n4.  선정된 입지의 위치(지번을 포함한다), 지목 및 면적\n② 법 제10조제1항 후단에서 \"대통령령으로 정하는 중요한 사항\"이란 다음 각 호의 사항을 말한다.\n1.  선정된 입지의 부지면적(100분의 30 이상 증가하는 경우로 한정한다)\n2.  공공폐자원관리시설의 종류\n3.  공공폐자원관리시설의 규모(100분의 30 이상 증가하는 경우로 한정한다)\n4.  선정된 입지의 위치\n③ 관리시설설치ㆍ운영기관은 법 제10조제1항에 따라 공공폐자원관리시설의 입지가 결정ㆍ고시된 경우에는 다음 각 호의 사항에 관한 서류를 첨부하여 국토교통부장관 또는 도시ㆍ군관리계획 결정권자에게 지체 없이 그 사실을 통지해야 한다.\n1.  제1항 각 호의 사항\n2.  공공폐자원관리시설 입지의 결정ㆍ고시일\n3.  도시ㆍ군관리계획상 용도지역별 면적\n4.  도시ㆍ군관리계획상 용도지역을 표시한 축척 5천분의 1 이상의 지형도(축척 5천분의 1 이상의 도시ㆍ군관리계획도가 작성되지 않은 지역의 경우에는 축척 2만5천분의 1 이상의 도면)\n5.  지정범위를 표시한 축척 1천200분의 1의 지적도(임야의 경우에는 축척 6천분의 1의 임야도)",
        "enforcement_date": "20251001",
        "relations": [],
        "images": [],
        "provision_id": "law:공공폐자원관리시설의설치운영및주민지원등에관한특별법시행령#JO0008"
      },
      {
        "article_no": "제9조",
        "article_title": "공공폐자원관리시설 입지 안의 주민에 대한 지원",
        "chapter": "제2장 공공폐자원관리시설의 설치ㆍ운영 등",
        "content": "제9조(공공폐자원관리시설 입지 안의 주민에 대한 지원)\n① 관리시설설치ㆍ운영기관이 법 제11조에 따라 지원을 하는 주민은 법 제10조제1항에 따른 공공폐자원관리시설 입지의 결정ㆍ고시일을 기준으로 해당 공공폐자원관리시설의 입지 안에 거주하는 사람으로서 다음 각 호의 어느 하나에 해당하는 사람으로 한다.\n1.  입지 안의 건축물 또는 토지의 소유자\n2.  입지 안의 무허가 건축물(신고하지 않고 건축한 건축물을 포함한다)의 소유자\n3.  제1호 또는 제2호에 따른 건축물의 세입자\n② 제1항제1호에 따른 지원대상자 중 1년 이상 거주한 사람과 제1항제2호 및 제3호에 따른 지원대상자 중 3년 이상 거주한 사람에 대해서는 가구당 1천만원의 이주정착지원금과 가구 구성원 1인당 200만원의 생활안정지원금을 지급하되, 가구당 총생활안정지원금은 800만원을 초과할 수 없다.\n③ 제1항제1호에 따른 지원대상자 중 1년 미만 거주한 사람과 제1항제2호 및 제3호에 따른 지원대상자 중 3년 미만 거주한 사람에 대해서는 「공익사업을 위한 토지 등의 취득 및 보상에 관한 법률」 제78조제6항에 따른 가재도구 등 동산의 운반에 필요한 비용을 지급한다. <개정 2022.5.9>\n④ 제1항에 따른 지원대상자는 이주정착지원금, 생활안정지원금 또는 제3항에 따른 비용을 지급받으려는 경우에는 이주 예정일 6개월 이전까지 관리시설설치ㆍ운영기관에 그 지급을 신청해야 한다.",
        "enforcement_date": "20251001",
        "relations": [],
        "images": [],
        "provision_id": "law:공공폐자원관리시설의설치운영및주민지원등에관한특별법시행령#JO0009"
      },
      {
        "article_no": "제10조",
        "article_title": "공공폐자원관리시설 입지 안에서의 행위제한 등",
        "chapter": "제2장 공공폐자원관리시설의 설치ㆍ운영 등",
        "content": "제10조(공공폐자원관리시설 입지 안에서의 행위제한 등)\n① 법 제11조에 따른 공공폐자원관리시설입지(이하 \"공공폐자원관리시설입지\"라 한다) 안에서 법 제13조제1항 각 호의 어느 하나에 해당하는 행위를 하려는 자는 같은 항 각 호 외의 부분 전단에 따라 기후에너지환경부령으로 정하는 허가신청서에 다음 각 호의 서류를 첨부하여 관할 특별자치시장, 특별자치도지사, 시장ㆍ군수ㆍ구청장(자치구의 구청장을 말한다. 이하 같다)에게 제출해야 한다. <개정 2025.10.1>\n1.  허가를 받으려는 행위에 관한 사항을 기재한 서류 또는 사업계획서\n2.  공사시행계획서\n3.  허가를 받으려는 지역의 위치를 표시한 지형도면\n② 법 제13조제1항 각 호 외의 부분 후단에서 \"대통령령으로 정하는 사항\"이란 다음 각 호의 사항을 말한다.\n1.  토지의 형질 변경 면적(허가받은 면적에 비해 100분의 20 이상 증가하는 경우로 한정한다)\n2.  건축물의 건축 연면적(허가받은 건축물의 연면적에 비해 100분의 20 이상 증가하는 경우로 한정한다)\n3.  공작물의 설치 면적(허가받은 면적에 비해 100분의 20 이상 증가하는 경우로 한정한다)\n③ 법 제13조제1항제5호에서 \"대통령령으로 정하는 토지의 분할 또는 물건의 야적(野積)\"이란 다음 각 호의 분할 또는 야적 행위를 말한다.\n1.  토지의 분할: 「건축법」 제57조에 따른 대지면적 최소한도 미만의 토지의 분할\n2.  물건의 야적: 무게가 3톤을 초과하는 물건의 야적. 다만, 5톤 미만의 물건으로서 그 물건의 각 부분이 3톤 이하로 쉽게 나누어질 수 있는 물건의 야적은 제외한다.",
        "enforcement_date": "20251001",
        "relations": [
          {
            "relation_type": "delegation",
            "delegation_type": "시행규칙",
            "target_category": "법령",
            "source_article_no": "제10조",
            "source_clause": "제10조제1항",
            "link_text": "기후에너지환경부령",
            "line_text": "기후에너지환경부령",
            "target_law_name": "공공폐자원관리시설의 설치ㆍ운영 및 주민지원 등에 관한 특별법 시행규칙",
            "target_article_no": "제4조",
            "target_article_title": "제한행위의 허가신청서",
            "target_mst": "278873",
            "target_url": "https://www.law.go.kr/법령/공공폐자원관리시설의 설치ㆍ운영 및 주민지원 등에 관한 특별법 시행규칙/제4조",
            "resolve_method": "lsDelegated",
            "source_provision_id": "law:공공폐자원관리시설의설치운영및주민지원등에관한특별법시행령#JO0010",
            "reference_id": "law:공공폐자원관리시설의설치운영및주민지원등에관한특별법시행규칙#JO0004"
          }
        ],
        "images": [],
        "provision_id": "law:공공폐자원관리시설의설치운영및주민지원등에관한특별법시행령#JO0010"
      },
      {
        "article_no": "제11조",
        "article_title": "공공폐자원관리시설 설치계획의 수립 및 승인 등",
        "chapter": "제2장 공공폐자원관리시설의 설치ㆍ운영 등",
        "content": "제11조(공공폐자원관리시설 설치계획의 수립 및 승인 등)\n① 법 제14조제1항제5호에서 \"대통령령으로 정하는 사항\"이란 다음 각 호의 사항을 말한다. <개정 2024.12.24>\n1.  공공폐자원관리시설입지 안에 거주하는 주민의 이주대책\n2.  소각시설에서 발생하는 소각재 등 폐기물의 처리계획\n3.  공공폐자원관리시설 내에 매립시설이 있는 경우 그 시설의 사후관리계획\n4.  「폐기물처리시설 설치촉진 및 주변지역지원 등에 관한 법률 시행령」 제12조제1항제8호에 따른 환경성 조사서\n5.  입지선정에 관한 인접 지방자치단체의 장과의 협의 결과(법 제9조제6항에 따른 협의를 한 경우로 한정한다)\n6.  입지선정에 관한 「환경분쟁 조정 및 환경피해 구제에 관한 법률」 제4조에 따른 중앙환경분쟁조정피해구제위원회의 조정 결과(법 제9조제6항에 해당하여 분쟁조정을 한 경우로 한정한다)\n② 법 제14조제6항에 따라 설치계획을 공고하는 경우에는 제6조제2항에 따른 방법으로 한다.\n③ 법 제14조제8항에서 \"대통령령으로 정하는 중요한 사항\"이란 다음 각 호의 사항을 말한다.\n1.  처리대상 폐기물의 종류 및 처리량\n2.  공공폐자원관리시설의 종류 및 규모(법 제14조제2항에 따라 승인을 받은 후의 총규모를 말한다). 다만, 해당 시설의 규모만 변경되는 경우로서 그 규모의 변경이 100분의 30 미만인 경우는 제외한다.\n3.  공공폐자원관리시설의 위치 및 부지의 면적\n4.  관리시설설치ㆍ운영기관\n5.  공공폐자원관리시설의 설치기간\n6.  폐기물처리 대상지역\n7.  공공폐자원관리시설입지 안에 거주하는 주민의 이주대책",
        "enforcement_date": "20251001",
        "relations": [],
        "images": [],
        "provision_id": "law:공공폐자원관리시설의설치운영및주민지원등에관한특별법시행령#JO0011"
      },
      {
        "article_no": "제12조",
        "article_title": "공공폐자원관리시설 반입수수료",
        "chapter": "제2장 공공폐자원관리시설의 설치ㆍ운영 등",
        "content": "제12조(공공폐자원관리시설 반입수수료)\n① 관리시설설치ㆍ운영기관은 다음 각 호의 경비를 고려하여 법 제20조제1항에 따른 반입수수료(이하 이 조에서 \"반입수수료\"라 한다)의 금액을 결정해야 한다.\n1.  폐기물의 종류별로 산정한 폐기물의 처리에 드는 적정 경비\n2.  민간 폐기물처리시설의 처리 단가\n3.  관리시설설치ㆍ운영기관이 폐기물을 직접 수집ㆍ운반하는 경우에는 그 수집ㆍ운반에 드는 경비\n4.  법 제31조제1항에 따른 운영이익금\n② 기후에너지환경부장관 외의 관리시설설치ㆍ운영기관이 제1항에 따라 반입수수료의 금액을 결정하거나 변경할 때에는 기후에너지환경부장관과 협의해야 한다. <개정 2025.10.1>\n③ 관리시설설치ㆍ운영기관은 제1항 및 제2항에 따라 결정하거나 변경한 반입수수료의 금액을 해당 기관의 인터넷 홈페이지를 통하여 공개해야 한다.\n④ 반입수수료는 공공처리대상폐기물을 공공폐자원관리시설에 반입할 때에 수입증지로 납부하거나 정보통신망을 이용한 전자결제 등의 방법으로 납부해야 한다.\n⑤ 관리시설설치ㆍ운영기관은 공공폐자원관리시설이 설치되어 있는 시ㆍ군ㆍ구에서 반입하는 공공처리대상폐기물에 대해서는 100분의 10 이내의 범위에서 반입수수료를 감면할 수 있으며, 그 감면 범위의 결정 및 공개 방법에 관하여는 제2항 및 제3항을 준용한다.",
        "enforcement_date": "20251001",
        "relations": [],
        "images": [],
        "provision_id": "law:공공폐자원관리시설의설치운영및주민지원등에관한특별법시행령#JO0012"
      },
      {
        "article_no": "제13조",
        "article_title": "주변영향지역의 결정ㆍ고시 및 이주대책",
        "chapter": "제3장 공공폐자원관리시설 운영에 따른 이익 공유 등",
        "content": "제13조(주변영향지역의 결정ㆍ고시 및 이주대책)\n① 법 제27조제1항에서 \"대통령령으로 정하는 기간\"이란 2년을 말한다.\n② 관리시설설치ㆍ운영기관은 법 제27조제1항에 따라 다음 각 호의 사항을 포함하여 공공폐자원관리시설의 설치ㆍ운영으로 인하여 환경 및 기타 일상생활에 영향을 받게 되는 주변영향지역(이하 \"주변영향지역\"이라 한다)을 결정ㆍ고시해야 한다.\n1.  공공폐자원관리시설의 명칭 및 관리시설설치ㆍ운영기관\n2.  공공폐자원관리시설의 위치(지번을 포함한다)ㆍ규모 및 명세\n3.  공공폐자원관리시설 설치공사의 착공 및 준공 예정일\n4.  주변영향지역의 범위(면적을 포함한다)\n③ 관리시설설치ㆍ운영기관은 법 제27조제1항에 따라 주변영향지역을 결정ㆍ고시한 후 환경상 영향의 변동이 있다고 인정되는 경우에는 주변영향지역을 조정하여 고시할 수 있다.\n④ 법 제28조에 따른 주민협의체(이하 \"주민협의체\"라 한다)는 법 제27조제2항에 따른 결과 수렴을 위하여 공공폐자원관리시설 설치계획이 공고된 날부터 90일(주민협의체 구성이 지연된 경우에는 그 구성일부터 30일을 말한다) 이내에 제7조제2항 각 호의 기관 중에서 환경과 그 밖의 일상생활에 미치는 영향조사(이하 \"환경상영향조사\"라 한다)를 실시할 연구기관을 선정하고, 그 결과를 관리시설설치ㆍ운영기관에 통보해야 한다.\n⑤ 관리시설설치ㆍ운영기관은 제4항에 따라 연구기관 선정 결과를 통보받은 경우 해당 연구기관으로 하여금 환경상영향조사를 하게 한 후 그 조사 결과를 수렴하여 주민협의체에 통지하고, 주변영향지역의 결정에 관한 사항을 주민협의체와 협의해야 한다.\n⑥ 법 제27조제3항제2호에 따른 기금수혜지역(이하 \"기금수혜지역\"이라 한다)의 범위는 다음 각 호와 같다. <개정 2025.10.1>\n1.  폐기물매립시설의 부지 경계로부터 2킬로미터 이내 지역\n2.  폐기물매립시설이 아닌 그 밖의 폐기물처리시설의 부지 경계로부터 300미터 이내 지역\n3.  제1호 또는 제2호의 지역 외의 지역으로서 관리시설설치ㆍ운영기관이 환경상영향조사 결과 기금수혜지역으로 포함할 필요가 있다고 기후에너지환경부장관과 협의하여 인정한 지역\n⑦ 법 제27조제5항 전단에 따라 토지ㆍ건축물 등의 매수를 청구하려는 자는 기후에너지환경부령으로 정하는 매수청구서에 다음 각 호의 서류를 첨부하여 해당 관리시설설치ㆍ운영기관에 제출해야 한다. <개정 2025.10.1>\n1.  토지등기부등본 등 매수청구 대상 토지의 위치ㆍ면적을 확인할 수 있는 서류\n2.  매수청구 대상 토지가 본인 소유임을 증명할 수 있는 서류\n⑧ 관리시설설치ㆍ운영기관은 법 제27조제5항에 따라 매수한 토지를 다음 각 호의 어느 하나에 해당하는 용도로 사용해야 한다.\n1.  공공폐자원관리시설의 운영으로 인한 주변 환경오염 측정을 위한 측정시설의 설치\n2.  공공폐자원관리시설의 방진ㆍ방음을 위한 시설의 설치\n3.  공공폐자원관리시설의 진입로 등 출입을 위한 시설의 설치\n4.  법 제32조제1항에 따른 해당 지역 주민을 위한 편익시설(이하 \"주민편익시설\"이라 한다)의 설치\n5.  공공폐자원관리시설이 설치된 지역의 대기오염, 소음, 악취 등 공해를 방지하기 위한 녹지(綠地)의 조성",
        "enforcement_date": "20251001",
        "relations": [
          {
            "relation_type": "delegation",
            "delegation_type": "시행규칙",
            "target_category": "법령",
            "source_article_no": "제13조",
            "source_clause": "제13조제7항",
            "link_text": "기후에너지환경부령",
            "line_text": "기후에너지환경부령",
            "target_law_name": "공공폐자원관리시설의 설치ㆍ운영 및 주민지원 등에 관한 특별법 시행규칙",
            "target_article_no": "제5조",
            "target_article_title": "매수청구서",
            "target_mst": "278873",
            "target_url": "https://www.law.go.kr/법령/공공폐자원관리시설의 설치ㆍ운영 및 주민지원 등에 관한 특별법 시행규칙/제5조",
            "resolve_method": "lsDelegated",
            "source_provision_id": "law:공공폐자원관리시설의설치운영및주민지원등에관한특별법시행령#JO0013",
            "reference_id": "law:공공폐자원관리시설의설치운영및주민지원등에관한특별법시행규칙#JO0005"
          }
        ],
        "images": [],
        "provision_id": "law:공공폐자원관리시설의설치운영및주민지원등에관한특별법시행령#JO0013"
      },
      {
        "article_no": "제14조",
        "article_title": "주민협의체의 구성 및 운영",
        "chapter": "제3장 공공폐자원관리시설 운영에 따른 이익 공유 등",
        "content": "제14조(주민협의체의 구성 및 운영)\n① 주민협의체의 구성 방법은 별표 2와 같다.\n② 주민협의체의 회의는 재적위원 3분의 1 이상이 요구하거나 주민협의체의 위원장(이하 \"위원장\"이라 한다)이 필요하다고 인정하는 경우에 소집하며, 위원장이 그 의장이 된다.\n③ 주민협의체의 회의는 재적위원 3분의 2 이상의 출석과 출석위원 과반수의 찬성으로 의결한다.\n④ 제2항 및 제3항에서 규정한 사항 외에 주민협의체의 운영에 필요한 사항은 주민협의체의 의결을 거쳐 위원장이 정한다.",
        "enforcement_date": "20251001",
        "relations": [
          {
            "relation_type": "appendix_ref",
            "delegation_type": null,
            "target_category": "별표",
            "source_article_no": "제14조",
            "source_clause": "제14조제1항",
            "link_text": "별표 2",
            "line_text": "① 주민협의체의 구성 방법은 별표 2와 같다.",
            "target_law_name": "공공폐자원관리시설의 설치ㆍ운영 및 주민지원 등에 관한 특별법 시행령",
            "target_article_no": "별표2",
            "target_article_title": "주민협의체의 구성 방법(제14조제1항 관련)",
            "appendix_no": "2",
            "appendix_branch": "",
            "appendix_kind": "별표",
            "appendix_found": true,
            "target_mst": "",
            "appendix_dangling": false,
            "target_url": "https://www.law.go.kr/LSW/lsBylInfoPLinkR.do?lsiSeq=278499&bylNo=0002&bylBrNo=00",
            "resolve_method": "text_parse",
            "source_provision_id": "law:공공폐자원관리시설의설치운영및주민지원등에관한특별법시행령#JO0014",
            "reference_id": "law:공공폐자원관리시설의설치운영및주민지원등에관한특별법시행령#BYL0002"
          }
        ],
        "images": [],
        "provision_id": "law:공공폐자원관리시설의설치운영및주민지원등에관한특별법시행령#JO0014"
      },
      {
        "article_no": "제15조",
        "article_title": "기금수혜지역의 운영이익금 지급대상 등",
        "chapter": "제3장 공공폐자원관리시설 운영에 따른 이익 공유 등",
        "content": "제15조(기금수혜지역의 운영이익금 지급대상 등)\n① 법 제29조제4항에 따라 지급하는 운영이익금(이하 이 조에서 \"기금수혜지역배분금\"이라 한다)의 지급대상은 기금수혜지역에 거주 또는 체류하고 있는 사람으로서 다음 각 호의 어느 하나에 해당하는 사람으로 한다.\n1.  「주민등록법」 제6조제1항제1호에 따른 거주자로서 공공폐자원관리시설입지의 결정ㆍ고시일을 기준으로 계속하여 6개월 이상 기금수혜지역에 주소가 등록되어 있는 사람\n2.  「재한외국인 처우 기본법」 제2조제3호에 따른 결혼이민자 또는 「출입국관리법」 제10조제2호에 따른 영주자격 취득자로서 공공폐자원관리시설입지의 결정ㆍ고시일을 기준으로 같은 법 제31조에 따라 계속하여 6개월 이상 기금수혜지역에 외국인등록이 되어 있는 사람\n3.  공공폐자원관리시설입지의 결정ㆍ고시일 당시 법 제27조제3항제1호의 이주지역에서 거주하다가 그 후 기금수혜지역으로 이주한 자로서 기금수혜지역에 주소가 등록되어 있거나 외국인등록이 되어 있는 사람\n② 기금수혜지역배분금은 세대별로 제1항 각 호에 해당하는 세대원 수에 따라 지급한다.\n③ 관리시설설치ㆍ운영기관은 기금수혜지역배분금 지급대상별 지급액 등 세부적인 사항을 정할 때에는 제17조에 따른 운영이익금의 배분 방법, 기금수혜지역에 거주 또는 체류하고 있는 주민 수 등을 고려해야 한다.\n④ 관리시설설치ㆍ운영기관은 제3항에 따른 사항을 기후에너지환경부장관과 협의하여 정하고, 이를 제6조제2항에 따른 방법으로 공고해야 한다. <개정 2025.10.1>",
        "enforcement_date": "20251001",
        "relations": [],
        "images": [],
        "provision_id": "law:공공폐자원관리시설의설치운영및주민지원등에관한특별법시행령#JO0015"
      },
      {
        "article_no": "제16조",
        "article_title": "주민투자 및 이익 공유",
        "chapter": "제3장 공공폐자원관리시설 운영에 따른 이익 공유 등",
        "content": "제16조(주민투자 및 이익 공유)\n① 법 제30조제1항에서 \"대통령령으로 정하는 인접 특별자치시, 시ㆍ군ㆍ구의 읍ㆍ면ㆍ동\"이란 다음 각 호의 지역을 말한다. <개정 2025.10.1>\n1.  기금수혜지역이 포함되어 있는 특별자치시, 시ㆍ군ㆍ구의 읍ㆍ면ㆍ동\n2.  제1호에 해당하지 않는 읍ㆍ면ㆍ동으로서 공공폐자원관리시설의 부지 경계로부터 5킬로미터 이내의 지역\n3.  그 밖에 공공폐자원관리시설입지에 연접한 특별자치시, 시ㆍ군ㆍ구의 읍ㆍ면ㆍ동으로서 주민의 투자가 저조하여 법 제30조제1항에 따른 투자참여지역(이하 \"투자참여지역\"이라 한다)을 확대할 필요가 있어 관리시설설치ㆍ운영기관이 기후에너지환경부장관과 협의하여 공고하는 읍ㆍ면ㆍ동\n② 관리시설설치ㆍ운영기관은 투자참여지역에 거주하는 주민을 대상으로 공공폐자원관리시설 설치사업에 대한 투자금을 다음 각 호의 방법으로 모집할 수 있다. <개정 2025.10.1>\n1.  주식 또는 채권 발행\n2.  그 밖에 투자금 모집을 위하여 필요하다고 기후에너지환경부장관이 인정하는 방법\n③ 제2항에 따른 투자금의 한도는 다음 각 호의 구분에 따른 범위에서 관리시설설치ㆍ운영기관이 결정한다.\n1.  투자금의 총한도: 공공폐자원관리시설의 설치비용(법 제29조제1항에 따른 주민특별기금으로 충당하는 금액은 제외한다)의 100분의 10 이하\n2.  투자자별 한도: 세대당 3천만원 이하\n④ 관리시설설치ㆍ운영기관은 투자 기간이 만료되는 등 반환 사유가 발생한 경우에는 투자금을 반환해야 한다.",
        "enforcement_date": "20251001",
        "relations": [],
        "images": [],
        "provision_id": "law:공공폐자원관리시설의설치운영및주민지원등에관한특별법시행령#JO0016"
      },
      {
        "article_no": "제17조",
        "article_title": "운영이익금의 배분",
        "chapter": "제3장 공공폐자원관리시설 운영에 따른 이익 공유 등",
        "content": "제17조(운영이익금의 배분) 법 제31조제1항에 따른 운영이익금의 산정 및 배분 방법, 배분한도 및 유보금의 적립ㆍ관리와 사용용도는 별표 3과 같다.",
        "enforcement_date": "20251001",
        "relations": [
          {
            "relation_type": "appendix_ref",
            "delegation_type": null,
            "target_category": "별표",
            "source_article_no": "제17조",
            "source_clause": "제17조",
            "link_text": "별표 3",
            "line_text": "제17조(운영이익금의 배분) 법 제31조제1항에 따른 운영이익금의 산정 및 배분 방법, 배분한도 및 유보금의 적립ㆍ관리와 사용용도는 별표 3과 같다.",
            "target_law_name": "공공폐자원관리시설의 설치ㆍ운영 및 주민지원 등에 관한 특별법 시행령",
            "target_article_no": "별표3",
            "target_article_title": "운영이익금의 산정 및 배분 방법 등(제17조 관련)",
            "appendix_no": "3",
            "appendix_branch": "",
            "appendix_kind": "별표",
            "appendix_found": true,
            "target_mst": "",
            "appendix_dangling": false,
            "target_url": "https://www.law.go.kr/LSW/lsBylInfoPLinkR.do?lsiSeq=278499&bylNo=0003&bylBrNo=00",
            "resolve_method": "text_parse",
            "source_provision_id": "law:공공폐자원관리시설의설치운영및주민지원등에관한특별법시행령#JO0017",
            "reference_id": "law:공공폐자원관리시설의설치운영및주민지원등에관한특별법시행령#BYL0003"
          }
        ],
        "images": [],
        "provision_id": "law:공공폐자원관리시설의설치운영및주민지원등에관한특별법시행령#JO0017"
      },
      {
        "article_no": "제18조",
        "article_title": "공공폐자원관리시설 설치지역의 주민지원 등",
        "chapter": "제3장 공공폐자원관리시설 운영에 따른 이익 공유 등",
        "content": "제18조(공공폐자원관리시설 설치지역의 주민지원 등)\n① 공공폐자원관리시설입지를 관할하는 특별자치시장, 특별자치도지사, 시장ㆍ군수ㆍ구청장(이하 \"관할 지방자치단체의 장\"이라 한다)의 법 제31조제1항제4호에 따른 지원금(이하 \"지원금\"이라 한다) 사용에 관하여는 「폐기물처리시설 설치촉진 및 주변지역지원 등에 관한 법률 시행령」 제27조제1항을 준용한다. 이 경우 \"폐기물처리시설 설치기관\"은 \"관할 지방자치단체의 장\"으로, \"주민지원기금\"은 \"지원금\"으로, \"지원협의체\"는 \"주민협의체\"로 본다.\n② 관할 지방자치단체의 장은 주민협의체와 협의하여 주변영향지역에 거주하는 주민에 대하여 조례로 정하는 바에 따라 주민편익시설의 사용료를 감면할 수 있다.\n③ 관할 지방자치단체의 장은 「은행법」에 따른 은행이나 체신관서에 별도의 계좌를 설정하여 지원금을 운용ㆍ관리해야 한다.\n④ 관할 지방자치단체의 장은 지원금을 그 총액의 100분의 5 범위에서 다음 각 호의 용도로 사용할 수 있다.\n1.  주민의 의견 수렴 및 주민협의체의 운영에 필요한 경비\n2.  제2항에 따라 주변영향지역에 거주하는 주민에 대하여 주민편익시설의 사용료를 감면하는 경우 사용료의 감면으로 인하여 발생하는 주민편익시설 운영비용 결손의 충당(주민협의체와 협의된 경우로 한정한다)\n⑤ 관할 지방자치단체의 장은 지원금의 조성 및 사용 실적을 해당 지방자치단체의 인터넷 홈페이지에 게재하는 방법으로 공개해야 한다.",
        "enforcement_date": "20251001",
        "relations": [
          {
            "relation_type": "citation",
            "delegation_type": null,
            "target_category": "법령",
            "source_article_no": "제18조",
            "source_clause": "제18조제3항",
            "link_text": "「은행법」",
            "line_text": "③ 관할 지방자치단체의 장은 「은행법」에 따른 은행이나 체신관서에 별도의 계좌를 설정하여 지원금을 운용ㆍ관리해야 한다.",
            "target_law_name": "은행법",
            "target_article_no": "",
            "target_article_title": "",
            "target_mst": "",
            "target_url": "https://www.law.go.kr/법령/은행법",
            "resolve_method": "text_parse",
            "source_provision_id": "law:공공폐자원관리시설의설치운영및주민지원등에관한특별법시행령#JO0018",
            "reference_id": "law:은행법#DOC"
          }
        ],
        "images": [],
        "provision_id": "law:공공폐자원관리시설의설치운영및주민지원등에관한특별법시행령#JO0018"
      },
      {
        "article_no": "제19조",
        "article_title": "지역주민의 감시",
        "chapter": "제4장 친환경적인 공공폐자원관리시설의 운영ㆍ관리",
        "content": "제19조(지역주민의 감시)\n① 법 제34조제1항에 따른 주민감시요원(이하 \"주민감시요원\"이라 한다)의 자격 및 인원은 별표 4와 같다.\n② 주민감시요원의 활동범위는 다음 각 호와 같다.\n1.  공공처리대상폐기물의 반입이 적절하게 이루어지고 있는지에 대한 확인\n2.  반입된 공공처리대상폐기물의 적정 처리 여부에 대한 확인",
        "enforcement_date": "20251001",
        "relations": [
          {
            "relation_type": "appendix_ref",
            "delegation_type": null,
            "target_category": "별표",
            "source_article_no": "제19조",
            "source_clause": "제19조제1항",
            "link_text": "별표 4",
            "line_text": "① 법 제34조제1항에 따른 주민감시요원(이하 \"주민감시요원\"이라 한다)의 자격 및 인원은 별표 4와 같다.",
            "target_law_name": "공공폐자원관리시설의 설치ㆍ운영 및 주민지원 등에 관한 특별법 시행령",
            "target_article_no": "별표4",
            "target_article_title": "주민감시요원의 자격 및 인원(제19조제1항 관련)",
            "appendix_no": "4",
            "appendix_branch": "",
            "appendix_kind": "별표",
            "appendix_found": true,
            "target_mst": "",
            "appendix_dangling": false,
            "target_url": "https://www.law.go.kr/LSW/lsBylInfoPLinkR.do?lsiSeq=278499&bylNo=0004&bylBrNo=00",
            "resolve_method": "text_parse",
            "source_provision_id": "law:공공폐자원관리시설의설치운영및주민지원등에관한특별법시행령#JO0019",
            "reference_id": "law:공공폐자원관리시설의설치운영및주민지원등에관한특별법시행령#BYL0004"
          }
        ],
        "images": [],
        "provision_id": "law:공공폐자원관리시설의설치운영및주민지원등에관한특별법시행령#JO0019"
      },
      {
        "article_no": "제20조",
        "article_title": "환경관리 강화 및 운영투명성 확보",
        "chapter": "제4장 친환경적인 공공폐자원관리시설의 운영ㆍ관리",
        "content": "제20조(환경관리 강화 및 운영투명성 확보)\n① 관리시설설치ㆍ운영기관은 법 제35조제2항에 따라 오염물질을 측정할 때에는 다음 각 호의 구분에 따라야 한다.\n1.  공공폐자원관리시설이 폐기물매립시설에 해당하는 경우: 「폐기물관리법」 제31조제2항에 따라 오염물질을 측정\n2.  공공폐자원관리시설이 그 밖의 폐기물처리시설로서 대기오염물질배출시설에 해당하는 경우: 「대기환경보전법」 제39조에 따라 오염물질을 측정\n② 관리시설설치ㆍ운영기관은 법 제35조제4항에 따라 주변영향지역에 미치는 환경상 영향을 조사할 때에는 주민협의체와의 협의를 거쳐 제7조제2항 각 호의 전문연구기관 중에서 조사 기관을 선정하여 조사하게 해야 한다.\n③ 제2항에 따른 환경상 영향조사의 주기ㆍ방법은 공공폐자원관리시설의 종류 및 규모에 따라 기후에너지환경부장관이 정하여 고시한다. <개정 2025.10.1>\n④ 관리시설설치ㆍ운영기관은 제1항에 따른 오염물질 측정 결과와 제2항에 따른 환경상 영향조사 결과를 제6조제2항에 따른 방법으로 공고하고, 관련 서류를 갖추어 해당 지역주민이 30일(토요일과 「관공서의 공휴일에 관한 규정」에 따른 공휴일을 제외하고 계산한다) 이상 열람할 수 있도록 해야 한다.\n⑤ 관리시설설치ㆍ운영기관은 제1항에 따른 오염물질 측정 결과를 기록하고, 공공폐자원관리시설의 운영이 끝날 때까지 보존해야 한다.",
        "enforcement_date": "20251001",
        "relations": [
          {
            "relation_type": "citation",
            "delegation_type": null,
            "target_category": "법령",
            "source_article_no": "제20조",
            "source_clause": "제20조제4항",
            "link_text": "「관공서의 공휴일에 관한 규정」",
            "line_text": "④ 관리시설설치ㆍ운영기관은 제1항에 따른 오염물질 측정 결과와 제2항에 따른 환경상 영향조사 결과를 제6조제2항에 따른 방법으로 공고하고, 관련 서류를 갖추어 해당 지역주민이 30일(토요일과 「관공서의 공휴일에 관한 규정」에 따른 공휴일을 제외하고 계산한다) 이상 열람할 수 있도록 해야 한다.",
            "target_law_name": "관공서의 공휴일에 관한 규정",
            "target_article_no": "",
            "target_article_title": "",
            "target_mst": "",
            "target_url": "https://www.law.go.kr/법령/관공서의 공휴일에 관한 규정",
            "resolve_method": "text_parse",
            "source_provision_id": "law:공공폐자원관리시설의설치운영및주민지원등에관한특별법시행령#JO0020",
            "reference_id": "law:관공서의공휴일에관한규정#DOC"
          }
        ],
        "images": [],
        "provision_id": "law:공공폐자원관리시설의설치운영및주민지원등에관한특별법시행령#JO0020"
      },
      {
        "article_no": "제21조",
        "article_title": "주민지원 사항의 의뢰",
        "chapter": "제4장 친환경적인 공공폐자원관리시설의 운영ㆍ관리",
        "content": "제21조(주민지원 사항의 의뢰) 관리시설설치ㆍ운영기관은 법 제36조제1항제2호에 따른 주민지원 사항을 다음 각 호의 어느 하나에 해당하는 자에게 의뢰하여 실시할 수 있다.\n1.  주민협의체\n2.  「협동조합 기본법」 제2조제3호에 따른 사회적협동조합 또는 「사회적기업 육성법」 제2조제1호에 따른 사회적기업(공공폐자원관리시설 주변지역 주민들로 구성된 사회적협동조합 또는 사회적기업으로 한정한다)",
        "enforcement_date": "20251001",
        "relations": [],
        "images": [],
        "provision_id": "law:공공폐자원관리시설의설치운영및주민지원등에관한특별법시행령#JO0021"
      },
      {
        "article_no": "제22조",
        "article_title": "폐기물처리시설의 매수",
        "chapter": "제4장 친환경적인 공공폐자원관리시설의 운영ㆍ관리",
        "content": "제22조(폐기물처리시설의 매수)\n① 법 제38조제1항에서 \"휴업 또는 폐업 등 대통령령으로 정하는 사유\"란 폐기물처리시설의 정상적인 운영이 불가능하게 된 다음 각 호의 어느 하나에 해당하는 사유를 말한다.\n1.  휴업 또는 폐업\n2.  허가 취소\n3.  파산 또는 회생절차의 개시\n② 법 제38조제1항에 따른 폐기물처리시설과 이에 부수되는 시설 및 토지(이하 \"폐기물처리시설등\"이라 한다)의 매수를 청구하려는 자는 기후에너지환경부령으로 정하는 매수청구서에 다음 각 호의 서류를 첨부하여 기후에너지환경부장관에게 제출해야 한다. <개정 2025.10.1>\n1.  토지 또는 건축물 대장, 토지 또는 건물 등기사항 증명서 및 토지이용계획확인서 등 폐기물처리시설등의 지번ㆍ지목ㆍ면적, 이용현황, 권리설정 현황 및 그 소유자임을 증명할 수 있는 서류\n2.  폐기물처리업 허가증 등 폐기물처리시설의 현황을 확인할 수 있는 서류\n③ 기후에너지환경부장관은 제2항에 따라 폐기물처리시설등의 매수 청구를 받은 경우 폐기물처리시설등에 대한 기술진단을 실시하여 매수 여부와 매수 가격을 결정하고, 이를 청구인에게 알려야 한다. <개정 2025.10.1>\n④ 제3항에 따른 폐기물처리시설등의 매수 가격은 「부동산 가격공시에 관한 법률」에 따른 공시지가를 기준으로 그 토지의 위치, 형상, 환경 및 이용 상황 등을 고려하여 평가한 금액으로 하되, 둘 이상의 감정평가법인등(「감정평가 및 감정평가사에 관한 법률」 제2조제4호에 따른 감정평가법인등을 말한다)이 평가한 금액을 산술평균한 금액으로 한다.\n⑤ 법 제38조제2항에서 \"대통령령으로 정하는 용도\"란 제13조제8항 각 호의 용도를 말한다.",
        "enforcement_date": "20251001",
        "relations": [
          {
            "relation_type": "delegation",
            "delegation_type": "시행규칙",
            "target_category": "법령",
            "source_article_no": "제22조",
            "source_clause": "제22조제2항",
            "link_text": "기후에너지환경부령",
            "line_text": "기후에너지환경부령",
            "target_law_name": "공공폐자원관리시설의 설치ㆍ운영 및 주민지원 등에 관한 특별법 시행규칙",
            "target_article_no": "제5조",
            "target_article_title": "매수청구서",
            "target_mst": "278873",
            "target_url": "https://www.law.go.kr/법령/공공폐자원관리시설의 설치ㆍ운영 및 주민지원 등에 관한 특별법 시행규칙/제5조",
            "resolve_method": "lsDelegated",
            "source_provision_id": "law:공공폐자원관리시설의설치운영및주민지원등에관한특별법시행령#JO0022",
            "reference_id": "law:공공폐자원관리시설의설치운영및주민지원등에관한특별법시행규칙#JO0005"
          },
          {
            "relation_type": "citation",
            "delegation_type": null,
            "target_category": "법령",
            "source_article_no": "제22조",
            "source_clause": "제22조제4항",
            "link_text": "「부동산 가격공시에 관한 법률」",
            "line_text": "④ 제3항에 따른 폐기물처리시설등의 매수 가격은 「부동산 가격공시에 관한 법률」에 따른 공시지가를 기준으로 그 토지의 위치, 형상, 환경 및 이용 상황 등을 고려하여 평가한 금액으로 하되, 둘 이상의 감정평가법인등(「감정평가 및 감정평가사에 관한 법률」 제2조제4호에 따른 감정평가법인등을 말한다)이 평가한 금액을 산술평균한 금액으로 한다.",
            "target_law_name": "부동산 가격공시에 관한 법률",
            "target_article_no": "",
            "target_article_title": "",
            "target_mst": "",
            "target_url": "https://www.law.go.kr/법령/부동산 가격공시에 관한 법률",
            "resolve_method": "text_parse",
            "source_provision_id": "law:공공폐자원관리시설의설치운영및주민지원등에관한특별법시행령#JO0022",
            "reference_id": "law:부동산가격공시에관한법률#DOC"
          }
        ],
        "images": [],
        "provision_id": "law:공공폐자원관리시설의설치운영및주민지원등에관한특별법시행령#JO0022"
      },
      {
        "article_no": "제23조",
        "article_title": "업무의 위탁",
        "chapter": "제5장 보칙",
        "content": "제23조(업무의 위탁)\n① 법 제39조에서 \"대통령령으로 정하는 자\"란 다음 각 호의 자를 말한다.\n1.  법 제6조제1항 각 호의 어느 하나에 해당하는 기관 또는 단체\n2.  해당 공공폐자원관리시설을 설계ㆍ시공한 자(해당 시설의 운영을 위탁하는 경우로 한정한다)\n② 기후에너지환경부장관은 제1항에 따른 자에게 공공폐자원관리시설의 관리ㆍ운영에 관한 업무의 일부를 위탁하는 경우에는 위탁받는 기관 및 위탁업무의 내용을 고시해야 한다. <개정 2025.10.1>",
        "enforcement_date": "20251001",
        "relations": [],
        "images": [],
        "provision_id": "law:공공폐자원관리시설의설치운영및주민지원등에관한특별법시행령#JO0023"
      },
      {
        "article_no": "제24조",
        "article_title": "고유식별정보의 처리",
        "chapter": "제5장 보칙",
        "content": "제24조(고유식별정보의 처리) 기후에너지환경부장관 또는 관리시설설치ㆍ운영기관은 다음 각 호의 사무를 수행하기 위하여 불가피한 경우 「개인정보 보호법 시행령」 제19조제1호에 따른 주민등록번호가 포함된 자료를 처리할 수 있다. <개정 2025.10.1>\n1.  법 제27조제5항에 따른 토지ㆍ건축물 등의 매수에 관한 사무\n2.  제22조에 따른 폐기물처리시설의 매수에 관한 사무",
        "enforcement_date": "20251001",
        "relations": [],
        "images": [],
        "provision_id": "law:공공폐자원관리시설의설치운영및주민지원등에관한특별법시행령#JO0024"
      }
    ]
  },
  "addenda": [
    {
      "promulgation_date": "20210608",
      "promulgation_no": "31746",
      "addendum_key": "2021060831746",
      "content": "부칙 <제31746호,2021.6.8>\n이 영은 2021년 6월 10일부터 시행한다. 다만, 제2조제1항제3호는 2021년 7월 22일부터 시행하고, 같은 항 제2호는 2021년 9월 10일부터 시행한다."
    },
    {
      "promulgation_date": "20220509",
      "promulgation_no": "32638",
      "addendum_key": "2022050932638",
      "content": "부칙(공익사업을 위한 토지 등의 취득 및 보상에 관한 법률 시행령) <제32638호,2022.5.9>\n제1조(시행일) 이 영은 2022년 8월 4일부터 시행한다.\n제2조(다른 법령의 개정) ① 공공폐자원관리시설의 설치ㆍ운영 및 주민지원 등에 관한 특별법 시행령 일부를 다음과 같이 개정한다.\n제9조제3항 중 \"「공익사업을 위한 토지 등의 취득 및 보상에 관한 법률」 제78조제5항\"을 \"「공익사업을 위한 토지 등의 취득 및 보상에 관한 법률」 제78조제6항\"으로 한다.\n②부터 ⑦까지 생략"
    },
    {
      "promulgation_date": "20241224",
      "promulgation_no": "35093",
      "addendum_key": "2024122435093",
      "content": "부칙(환경분쟁 조정 및 환경피해 구제 등에 관한 법률 시행령) <제35093호,2024.12.24>\n제1조(시행일) 이 영은 2025년 1월 1일부터 시행한다.\n제2조(다른 법령의 개정) ① 공공폐자원관리시설의 설치ㆍ운영 및 주민지원 등에 관한 특별법 시행령 일부를 다음과 같이 개정한다.\n제11조제1항제6호 중 \"「환경분쟁 조정법」 제4조에 따른 중앙환경분쟁조정위원회\"를 \"「환경분쟁 조정 및 환경피해 구제에 관한 법률」 제4조에 따른 중앙환경분쟁조정피해구제위원회\"로 한다.\n② 및 ③ 생략"
    },
    {
      "promulgation_date": "20251001",
      "promulgation_no": "35804",
      "addendum_key": "2025100135804",
      "content": "부칙(기후에너지환경부와 그 소속기관 직제) <제35804호,2025.10.1>\n제1조(시행일) 이 영은 공포한 날부터 시행한다. 다만, 부칙 제6조에 따라 개정되는 대통령령 중 이 영 시행 전에 공포되었으나 시행일이 도래하지 아니한 대통령령을 개정한 부분은 각각 해당 대통령령의 시행일부터 시행한다.\n제2조 부터 제4조까지 생략\n제5조(다른 법령의 개정) ①부터 ③까지 생략\n④ 공공폐자원관리시설의 설치ㆍ운영 및 주민지원 등에 관한 특별법 시행령 일부를 다음과 같이 개정한다.\n제2조제1항제4호, 같은 조 제2항, 제5조제1항, 제6조제2항제1호ㆍ제2호, 제8조제1항 각 호 외의 부분, 제12조제2항, 제13조제6항제3호, 제15조제4항, 제16조제1항제3호, 같은 조 제2항제2호, 제20조제3항, 제22조제2항 각 호 외의 부분, 같은 조 제3항, 제23조제2항 및 제24조 각 호 외의 부분 중 \"환경부장관\"을 각각 \"기후에너지환경부장관\"으로 한다.\n제5조제1항 및 제6조제2항제1호 중 \"환경부의\"를 각각 \"기후에너지환경부의\"로 한다.\n제10조제1항 각 호 외의 부분, 제13조제7항 각 호 외의 부분 및 제22조제2항 각 호 외의 부분 중 \"환경부령\"을 각각 \"기후에너지환경부령\"으로 한다.\n별표 1 제1호가목5)ㆍ7), 같은 호 나목5)ㆍ7), 별표 3 제1호2) 및 같은 표 제4호 중 \"환경부장관\"을 각각 \"기후에너지환경부장관\"으로 한다.\n별표 1 제1호가목6) 및 같은 호 나목6) 중 \"환경부\"를 각각 \"기후에너지환경부\"로 한다.\n⑤부터 <80>까지 생략"
    }
  ],
  "appendices": [
    {
      "no": "0001",
      "branch": "00",
      "kind": "별표",
      "title": "입지선정위원회의 구성 방법(제7조제1항 관련)",
      "enforcement_date": "20251001",
      "content": "■ 공공폐자원관리시설의 설치ㆍ운영 및 주민지원 등에 관한 특별법 시행령 [별표 1] <개정 2025. 10. 1.>\n입지선정위원회의 구성 방법(제7조제1항 관련)\n\n┌──────────────────────────────────────────────────┐\n│1. 입지선정위원회는 다음 각 호의 구분에 따른 기준으로 구성한다.                                     │\n│  가. 입지후보지가 하나의 지역인 경우                                                               │\n│    1) 입지후보지 관할 시ㆍ군ㆍ구(이하 이 표에서 “시ㆍ군ㆍ구”라 한다) 의회에서 선                 │\n│정한 주민대표 4명                                                                                   │\n│    2) 시ㆍ군ㆍ구 의회 의원 2명                                                                     │\n│    3) 시ㆍ군ㆍ구 의회가 추천한 전문가 2명                                                          │\n│    4) 시ㆍ군ㆍ구 공무원 1명                                                                        │\n│    5) 기후에너지환경부장관이 선정한 전문가 2명                                                     │\n│    6) 기후에너지환경부 소속 공무원 1명                                                             │\n│    7) 관리시설설치ㆍ운영기관 임직원 1명(기후에너지환경부장관 외의 관리시설설치                     │\n│ㆍ운영기관인 경우로 한정한다)                                                                       │\n│  나. 입지후보지가 둘 이상의 지역인 경우                                                            │\n│    1) 시ㆍ군ㆍ구 의회에서 선정한 주민대표: 시ㆍ군ㆍ구별 2명                                        │\n│    2) 시ㆍ군ㆍ구 의회 의원: 시ㆍ군ㆍ구별 1명                                                       │\n│    3) 시ㆍ군ㆍ구 의회가 추천한 전문가: 시ㆍ군ㆍ구별 1명                                            │\n│    4) 시ㆍ군ㆍ구 공무원: 시ㆍ군ㆍ구별 1명                                                          │\n│    5) 기후에너지환경부장관이 선정한 전문가 2명                                                     │\n│    6) 기후에너지환경부 소속 공무원 1명                                                             │\n│    7) 관리시설설치ㆍ운영기관 임직원 1명(기후에너지환경부장관 외의 관리시설설치                     │\n│ㆍ운영기관인 경우로 한정한다)                                                                       │\n│2. 입지선정위원회의 위원장은 위원회의 의결에 따라 선임한다.                                         │\n└──────────────────────────────────────────────────┘\n\n\n비고\n1. 주민대표는 해당 시ㆍ군ㆍ구에 거주하는 주민 중에서 선정하되, 입지후보지에 거\n주하는 주민대표를 1명(입지후보지가 하나의 지역인 경우에는 2명) 이상 포함해야\n한다. 다만, 입지후보지에 거주하는 주민이 없거나 입지후보지에 거주하는 주민 중\n입지선정위원회에 참여하려는 주민이 없는 경우에는 그렇지 않다.\n2. 전문가는 폐기물에 관한 전문지식과 실무경험이 풍부하다고 인정되는 다음 각 목\n의 어느 하나에 해당하는 사람으로 한다.\n가. 「고등교육법」 제2조에 따른 학교의 환경 관련 학과의 조교수 이상인 사람\n나. 국공립연구기관의 환경 분야 연구원으로서 연구경력이 5년 이상인 사람\n다. 환경 관련 분야의 박사학위 취득자\n라. 환경 관련 분야에 10년 이상 종사한 사람\n마. 갈등관리분야 전문가",
      "is_file_only": false,
      "view_url": "https://www.law.go.kr/LSW/lsBylInfoPLinkR.do?lsiSeq=278499&bylNo=0001&bylBrNo=00",
      "file_url": "https://www.law.go.kr/LSW/flDownload.do?flSeq=156952715",
      "files": [
        {
          "type": "hwp",
          "url": "https://www.law.go.kr/LSW/flDownload.do?flSeq=156952713",
          "name": "law0140942025100135804KC_000100E_20251001.hwp"
        },
        {
          "type": "pdf",
          "url": "https://www.law.go.kr/LSW/flDownload.do?flSeq=156952715",
          "name": "law0140942025100135804KC_000100E_20251001.pdf"
        },
        {
          "type": "image",
          "url": "https://www.law.go.kr/LSW/flDownload.do?flSeq=156952717",
          "name": "000100110201_P1_20251001.gif"
        },
        {
          "type": "image",
          "url": "https://www.law.go.kr/LSW/flDownload.do?flSeq=156952719",
          "name": "000100110201_P2_20251001.gif"
        }
      ],
      "images": [],
      "provision_id": "law:공공폐자원관리시설의설치운영및주민지원등에관한특별법시행령#BYL0001"
    },
    {
      "no": "0002",
      "branch": "00",
      "kind": "별표",
      "title": "주민협의체의 구성 방법(제14조제1항 관련)",
      "enforcement_date": "20251001",
      "content": "■ 공공폐자원관리시설의 설치ㆍ운영 및 주민지원 등에 관한 특별법 시행령 [별표 2]\n주민협의체의 구성 방법(제14조제1항 관련)\n\n┌─────────────────────────────────────────┐\n│1. 주민협의체의 정원                                                              │\n│  공공폐자원관리시설의 면적이 100만제곱미터 이상인 경우에는 21명 이내로, 100만제  │\n│곱미터 미만인 경우에는 15명 이내로 성별을 고려하여 구성한다.                      │\n│2. 주민협의체 위원의 자격                                                         │\n│  주민협의체는 공공폐자원관리시설로부터의 거리, 환경상 영향의 정도, 주민 수 등을  │\n│고려하여 제1호에 따른 정원의 범위에서 관리시설설치ㆍ운영기관이 관할 지방자치      │\n│단체의 장 및 해당 의회와 협의하여 다음 각 목의 사람으로 구성하되, 가목에 따른     │\n│주민대표가 정원 중 과반수가 되도록 해야 한다. 다만, 주변영향지역에 거주하는 주    │\n│민 수가 적어 과반수의 주민대표로 구성할 수 없는 경우에는 그렇지 않다.             │\n│  가. 주변영향지역(주변영향지역이 결정ㆍ고시되지 않은 때에는 폐기물매립시설의     │\n│경우 부지 경계선으로부터 2킬로미터 이내, 그 밖의 폐기물처리시설의 경우 부지       │\n│경계선으로부터 300미터 이내의 지역을 말한다. 이하 같다)에 거주하는 지역주민       │\n│으로서 해당 시ㆍ군ㆍ구 의회에서 추천한 읍ㆍ면ㆍ동별 주민대표                      │\n│  나. 공공폐자원관리시설이 설치된 지역을 관할하는 시ㆍ군ㆍ구 의회 의원            │\n│  다. 관할 지방자치단체의 장이 추천한 전문가 2명                                  │\n│3. 주민협의체 위원의 임기                                                         │\n│  주민협의체 위원의 임기는 2년으로 하며, 한 차례만 연임할 수 있다.                │\n│4. 위원장은 주민협의체의 의결을 거쳐 위원 중에서 선임한다.                        │\n└─────────────────────────────────────────┘\n\n\n비고\n1. 위 표 제2호 가목에도 불구하고 주변영향지역에 주민이 거주하지 않는 경우에는\n주민대표 대신 해당 시ㆍ군ㆍ구 의회 의원 4명과 관할 지방자치단체의 장이 추천\n한 전문가 2명으로 주민협의체를 구성한다.\n2. 전문가는 폐기물에 관한 전문지식과 실무경험이 풍부하다고 인정되는 다음 각 목\n의 어느 하나에 해당하는 사람으로 한다.\n가. 「고등교육법」 제2조에 따른 학교의 환경 관련 학과의 조교수 이상인 사람\n나. 국공립연구기관의 환경 분야 연구원으로서 연구경력이 5년 이상인 사람\n다. 환경 관련 분야의 박사학위 취득자\n라. 환경 관련 분야에 10년 이상 종사한 사람\n마. 갈등관리분야 전문가",
      "is_file_only": false,
      "view_url": "https://www.law.go.kr/LSW/lsBylInfoPLinkR.do?lsiSeq=278499&bylNo=0002&bylBrNo=00",
      "file_url": "https://www.law.go.kr/LSW/flDownload.do?flSeq=156952723",
      "files": [
        {
          "type": "hwp",
          "url": "https://www.law.go.kr/LSW/flDownload.do?flSeq=156952721",
          "name": "law0140942025100135804KC_000200E_20251001.hwp"
        },
        {
          "type": "pdf",
          "url": "https://www.law.go.kr/LSW/flDownload.do?flSeq=156952723",
          "name": "law0140942025100135804KC_000200E_20251001.pdf"
        },
        {
          "type": "image",
          "url": "https://www.law.go.kr/LSW/flDownload.do?flSeq=156952725",
          "name": "000200110201_P1_20251001.gif"
        }
      ],
      "images": [],
      "provision_id": "law:공공폐자원관리시설의설치운영및주민지원등에관한특별법시행령#BYL0002"
    },
    {
      "no": "0003",
      "branch": "00",
      "kind": "별표",
      "title": "운영이익금의 산정 및 배분 방법 등(제17조 관련)",
      "enforcement_date": "20251001",
      "content": "■ 공공폐자원관리시설의 설치ㆍ운영 및 주민지원 등에 관한 특별법 시행령 [별표 3] <개정 2025. 10. 1.>\n운영이익금의 산정 및 배분 방법 등(제17조 관련)\n\n1. 운영이익금의 산정 방법\n운영이익금은 총수익에서 총비용을 뺀 금액으로 산정한다.\n1) “총수익”은 법 제20조제1항에 따른 반입수수료와 그 밖의 수입을 합한 금액으로\n한다.\n2) “총비용”은 인건비, 유지ㆍ관리비용, 제세공과금 및 그 밖에 기후에너지환경부\n장관이 인정하는 비용을 합한 금액으로 한다.\n2. 운영이익금의 배분 방법\n가. 관리시설설치ㆍ운영기관은 매 사업연도의 결산에 따른 운영이익금을 다음 표의\n배분비율에 따라 배분한다.\n┌────────────────────────┬────────┐\n│배분 대상(법 제31조제1항 각 호)                 │배분비율        │\n├────────────────────────┼────────┤\n│1) 법 제29조제4항에 따른 기금수혜지역에 거주하  │100분의 10      │\n│는 세대에 배분해야 할 금액                      │                │\n├────────────────────────┼────────┤\n│2) 법 제30조제2항에 따른 투자참여지역 주민투자  │100분의 10 이내 │\n│자에게 배분해야 할 금액                         │                │\n├────────────────────────┼────────┤\n│3) 법 제32조제1항에 따른 관할 지방자치단체의 장 │100분의 40 ×   │\n│에 대한 지원금 및 법 제36조제1항에 따른 주민    │(1-공제율*)     │\n│지원 사항을 이행하기 위한 지원금                │                │\n├────────────────────────┼────────┤\n│4) 법 제30조제4항에 따른 투자금 반환, 그 밖에 공│100분의 20 이내 │\n│공폐자원관리시설의 운영을 목적으로 적립하는     │                │\n│유보금                                          │                │\n├────────────────────────┼────────┤\n│5) 국고지원 회수금                              │잔여 운영이익금 │\n└────────────────────────┴────────┘\n* “공제율”은 공공폐자원관리시설의 총반입수수료에서 공공폐자원관리시설이 설\n치된 관할 시ㆍ군ㆍ구의 방치폐기물ㆍ부적정처리폐기물에 대한 반입수수료가\n차지하는 비율을 말한다.\n나. 가목에도 불구하고, 관리시설설치ㆍ운영기관은 주민협의체와 협의하여 가목1)부\n터 3)까지의 배분비율 합계의 범위에서 각각의 배분비율을 조정할 수 있다. 이 경\n우 조정된 배분비율은 제6조제2항에 따른 방법으로 공고해야 한다.\n3. 제2호가목4)에 따라 적립한 유보금은 다음 각 목의 용도로 사용해야 한다.\n가. 주민투자금의 반환\n나. 공공폐자원관리시설 중 매립시설의 사후관리\n다. 운영손실금의 보전\n4. 관리시설설치ㆍ운영기관은 제1호부터 제3호까지에서 규정한 사항 외에 운영이익금\n의 산정 및 배분 방법 등에 필요한 사항은 기후에너지환경부장관과 협의하여 정하고,\n이를 제6조제2항에 따른 방법으로 공고해야 한다.",
      "is_file_only": false,
      "view_url": "https://www.law.go.kr/LSW/lsBylInfoPLinkR.do?lsiSeq=278499&bylNo=0003&bylBrNo=00",
      "file_url": "https://www.law.go.kr/LSW/flDownload.do?flSeq=156952729",
      "files": [
        {
          "type": "hwp",
          "url": "https://www.law.go.kr/LSW/flDownload.do?flSeq=156952727",
          "name": "law0140942025100135804KC_000300E_20251001.hwp"
        },
        {
          "type": "pdf",
          "url": "https://www.law.go.kr/LSW/flDownload.do?flSeq=156952729",
          "name": "law0140942025100135804KC_000300E_20251001.pdf"
        },
        {
          "type": "image",
          "url": "https://www.law.go.kr/LSW/flDownload.do?flSeq=156952731",
          "name": "000300110201_P1_20251001.gif"
        },
        {
          "type": "image",
          "url": "https://www.law.go.kr/LSW/flDownload.do?flSeq=156952733",
          "name": "000300110201_P2_20251001.gif"
        }
      ],
      "images": [],
      "provision_id": "law:공공폐자원관리시설의설치운영및주민지원등에관한특별법시행령#BYL0003"
    },
    {
      "no": "0004",
      "branch": "00",
      "kind": "별표",
      "title": "주민감시요원의 자격 및 인원(제19조제1항 관련)",
      "enforcement_date": "20251001",
      "content": "■ 공공폐자원관리시설의 설치ㆍ운영 및 주민지원 등에 관한 특별법 시행령 [별표 4]\n주민감시요원의 자격 및 인원(제19조제1항 관련)\n\n1. 주민감시요원의 자격\n가. 주민감시요원은 주변영향지역에 2년 이상 계속하여 거주하고 있는 주민 또는 환\n경분야에 관한 학식과 경험이 풍부한 전문가 중에서 주민협의체에서 추천한 사람\n을 관리시설설치ㆍ운영기관이 위촉한다. 다만, 법 제28조제1항제1호부터 제5호까\n지의 어느 하나에 해당하는 사람은 주민감시요원이 될 수 없다.\n나. 관리시설설치ㆍ운영기관은 주민감시요원이 다음의 어느 하나에 해당하는 경우\n에는 주민협의체에 그 사실을 통보하고, 그 주민감시요원을 해촉할 수 있다. 다만,\n3) 및 4)의 경우에는 주민감시요원을 해촉해야 한다.\n1) 감시활동과 관련하여 금품수수 등 부정한 행위를 한 경우\n2) 정당한 사유 없이 폐기물처리시설의 운영ㆍ관리를 방해하거나 운영ㆍ관리에\n지장을 주는 행위를 한 경우\n3) 법 제28조제1항제1호부터 제5호까지의 어느 하나에 해당하게 된 경우\n4) 거짓이나 그 밖의 부정한 방법으로 위촉된 경우\n5) 관리시설설치ㆍ운영기관이 정한 주민감시요원의 복무규정을 반복하여 위반하\n는 등 감시활동을 정상적으로 수행하지 않은 경우\n6) 심신장애로 인하여 직무를 수행할 수 없는 경우\n7) 주민감시요원 스스로 직무를 수행하는 것이 곤란하다고 의사를 밝히는 경우\n2. 주민감시요원의 인원\n주민감시요원의 인원은 공공처리대상폐기물의 반입량을 고려하여 다음 각 목에 따\n라 산정한 수의 범위에서 관리시설설치ㆍ운영기관이 주민협의체와 협의하여 정하\n되, 공공처리대상폐기물의 반입시간이 1일 9시간 이상인 때에는 이를 초과하는 매\n시간마다 그 산정된 수의 100분의 20씩(소수점 이하는 반올림한다) 늘릴 수 있다. 다만,\n늘린 인원은 다음 각 목에 따라 산정한 수의 100분의 50을 초과해서는 안 된다.\n가. 1일 평균 공공처리대상폐기물 반입량(신규시설의 경우에는 계획반입량을 말하\n고, 운영 중인 시설의 경우에는 전년도 총반입량을 실제 반입일수로 나눈 값을 말\n한다)을 150톤으로 나눈 수에 1을 더한 수(소수점 이하는 반올림한다) 이내\n나. 가목에 따른 산정 결과 2명 미만인 경우에는 2명 이내, 10명을 초과하는 경우에\n는 10명 이내",
      "is_file_only": false,
      "view_url": "https://www.law.go.kr/LSW/lsBylInfoPLinkR.do?lsiSeq=278499&bylNo=0004&bylBrNo=00",
      "file_url": "https://www.law.go.kr/LSW/flDownload.do?flSeq=156952737",
      "files": [
        {
          "type": "hwp",
          "url": "https://www.law.go.kr/LSW/flDownload.do?flSeq=156952735",
          "name": "law0140942025100135804KC_000400E_20251001.hwp"
        },
        {
          "type": "pdf",
          "url": "https://www.law.go.kr/LSW/flDownload.do?flSeq=156952737",
          "name": "law0140942025100135804KC_000400E_20251001.pdf"
        },
        {
          "type": "image",
          "url": "https://www.law.go.kr/LSW/flDownload.do?flSeq=156952739",
          "name": "000400110201_P1_20251001.gif"
        }
      ],
      "images": [],
      "provision_id": "law:공공폐자원관리시설의설치운영및주민지원등에관한특별법시행령#BYL0004"
    }
  ],
  "ordinance_delegations": [],
  "relation_stats": {
    "relations_total": 16,
    "by_category": {
      "법령": 11,
      "별표": 5
    },
    "by_relation_type": {
      "citation": 8,
      "appendix_ref": 5,
      "delegation": 3
    },
    "articles_total": 24,
    "articles_with_relations": 12,
    "unmatched_relations": 0,
    "ordinance_groups": 0,
    "ordinance_docs_total": 0,
    "addenda_count": 4,
    "appendices_count": 4
  },
  "source": {
    "source_url": "https://www.law.go.kr/법령/공공폐자원관리시설의 설치ㆍ운영 및 주민지원 등에 관한 특별법 시행령"
  },
  "provision_id": "law:공공폐자원관리시설의설치운영및주민지원등에관한특별법시행령#DOC",
  "future_enforcement_dates": [],
  "version_count": 1
}